{
  "1990": [
    {
      "url": "https://120minutes.org/video/042290/sinead+oconnor+nothing+compares+2+u",
      "name": "Sinead O'Connor | Nothing Compares 2 U",
      "youtubeUrl": "https://www.youtube.com/watch?v=0-EF60neguk",
      "youtubeId": "0-EF60neguk",
      "visitas": "547484945",
      "fecha": "22/04/1990"
    },
    {
      "url": "https://120minutes.org/video/042990/depeche+mode+enjoy+the+silence",
      "name": "Depeche Mode | Enjoy The Silence",
      "youtubeUrl": "https://www.youtube.com/watch?v=-_3dc6X-Iwo",
      "youtubeId": "-_3dc6X-Iwo",
      "visitas": "263400258",
      "fecha": "29/04/1990"
    },
    {
      "url": "https://120minutes.org/video/082690/depeche+mode+personal+jesus",
      "name": "Depeche Mode | Personal Jesus",
      "youtubeUrl": "https://www.youtube.com/watch?v=u1xrNaTO1bI",
      "youtubeId": "u1xrNaTO1bI",
      "visitas": "211154677",
      "fecha": "26/08/1990"
    },
    {
      "url": "https://120minutes.org/video/090290/too+much+joy+thats+a+lie",
      "name": "Too Much Joy | That's A Lie",
      "youtubeUrl": "https://www.youtube.com/watch?v=awexlghI7gM",
      "youtubeId": "awexlghI7gM",
      "visitas": "134302469",
      "fecha": "02/09/1990"
    },
    {
      "url": "https://120minutes.org/video/081990/depeche+mode+policy+of+truth",
      "name": "Depeche Mode | Policy Of Truth",
      "youtubeUrl": "https://www.youtube.com/watch?v=M2VBmHOYpV8",
      "youtubeId": "M2VBmHOYpV8",
      "visitas": "122173870",
      "fecha": "19/08/1990"
    },
    {
      "url": "https://120minutes.org/video/122390/the+cure+pictures+of+you",
      "name": "The Cure | Pictures Of You",
      "youtubeUrl": "https://www.youtube.com/watch?v=UmFFTkjs-O0",
      "youtubeId": "UmFFTkjs-O0",
      "visitas": "119391917",
      "fecha": "23/12/1990"
    },
    {
      "url": "https://120minutes.org/video/122390/the+cure+lullaby",
      "name": "The Cure | Lullaby",
      "youtubeUrl": "https://www.youtube.com/watch?v=ijxk-fgcg7c",
      "youtubeId": "ijxk-fgcg7c",
      "visitas": "97007050",
      "fecha": "23/12/1990"
    },
    {
      "url": "https://120minutes.org/video/102890/joy+division+love+will+tear+us+apart",
      "name": "Joy Division | Love Will Tear Us Apart",
      "youtubeUrl": "https://www.youtube.com/watch?v=zuuObGsB0No",
      "youtubeId": "zuuObGsB0No",
      "visitas": "91935898",
      "fecha": "28/10/1990"
    },
    {
      "url": "https://120minutes.org/video/122390/the+cure+lovesong",
      "name": "The Cure | Lovesong",
      "youtubeUrl": "https://www.youtube.com/watch?v=ks_qOI0lzho",
      "youtubeId": "ks_qOI0lzho",
      "visitas": "91485966",
      "fecha": "23/12/1990"
    },
    {
      "url": "https://120minutes.org/video/122390/the+cure+inbetween+days",
      "name": "The Cure | Inbetween Days",
      "youtubeUrl": "https://www.youtube.com/watch?v=scif2vfg1ug",
      "youtubeId": "scif2vfg1ug",
      "visitas": "55221121",
      "fecha": "23/12/1990"
    },
    {
      "url": "https://120minutes.org/video/010790/echo+the+bunnymen+killing+moon",
      "name": "Echo & The Bunnymen | Killing Moon",
      "youtubeUrl": "https://www.youtube.com/watch?v=LWz0JC7afNQ",
      "youtubeId": "LWz0JC7afNQ",
      "visitas": "52843038",
      "fecha": "07/01/1990"
    },
    {
      "url": "https://120minutes.org/video/111190/social+distortion+story+of+my+life",
      "name": "Social Distortion | Story of My Life",
      "youtubeUrl": "https://www.youtube.com/watch?v=oh8zcbC_Dcw",
      "youtubeId": "oh8zcbC_Dcw",
      "visitas": "45675993",
      "fecha": "11/11/1990"
    },
    {
      "url": "https://120minutes.org/video/123090/depeche+mode+world+in+my+eyes",
      "name": "Depeche Mode  | World In My Eyes",
      "youtubeUrl": "https://www.youtube.com/watch?v=nhZdL4JlnxI",
      "youtubeId": "nhZdL4JlnxI",
      "visitas": "45381877",
      "fecha": "30/12/1990"
    },
    {
      "url": "https://120minutes.org/video/091690/candy+iggy+pop+and+kate+pierson",
      "name": "Candy  | Iggy Pop and Kate Pierson",
      "youtubeUrl": "https://www.youtube.com/watch?v=6bLOjmY--TA",
      "youtubeId": "6bLOjmY--TA",
      "visitas": "33930599",
      "fecha": "16/09/1990"
    },
    {
      "url": "https://120minutes.org/video/050690/the+smiths+the+boy+with+a+thorn+in+his+side",
      "name": "The Smiths | The Boy with a Thorn in His Side",
      "youtubeUrl": "https://www.youtube.com/watch?v=qdOHPjMzY8s",
      "youtubeId": "qdOHPjMzY8s",
      "visitas": "27798274",
      "fecha": "06/05/1990"
    },
    {
      "url": "https://120minutes.org/video/071590/nine+inch+nails+head+like+a+hole",
      "name": "Nine Inch Nails | Head Like A Hole",
      "youtubeUrl": "https://www.youtube.com/watch?v=ao-Sahfy7Hg",
      "youtubeId": "ao-Sahfy7Hg",
      "visitas": "25163976",
      "fecha": "15/07/1990"
    },
    {
      "url": "https://120minutes.org/video/061790/the+church+under+the+milky+way",
      "name": "The Church | Under The Milky Way",
      "youtubeUrl": "https://www.youtube.com/watch?v=pWxJEIz7sSA",
      "youtubeId": "pWxJEIz7sSA",
      "visitas": "25017482",
      "fecha": "17/06/1990"
    },
    {
      "url": "https://120minutes.org/video/071590/concrete+blonde+joey",
      "name": "Concrete Blonde | Joey",
      "youtubeUrl": "https://www.youtube.com/watch?v=OdpTcvSn8HQ",
      "youtubeId": "OdpTcvSn8HQ",
      "visitas": "24500755",
      "fecha": "15/07/1990"
    },
    {
      "url": "https://120minutes.org/video/071590/iggy+pop+real+wild+child+wild+one",
      "name": "Iggy Pop | Real Wild Child (Wild One)",
      "youtubeUrl": "https://www.youtube.com/watch?v=def3ob2h-1s",
      "youtubeId": "def3ob2h-1s",
      "visitas": "24412439",
      "fecha": "15/07/1990"
    },
    {
      "url": "https://120minutes.org/video/010790/the+specials+ghost+town",
      "name": "The Specials | Ghost Town",
      "youtubeUrl": "https://www.youtube.com/watch?v=RZ2oXzrnti4",
      "youtubeId": "RZ2oXzrnti4",
      "visitas": "23846334",
      "fecha": "07/01/1990"
    },
    {
      "url": "https://120minutes.org/video/050690/the+cure+lovecats",
      "name": "The Cure | Lovecats",
      "youtubeUrl": "https://www.youtube.com/watch?v=mcUza_wWCfA",
      "youtubeId": "mcUza_wWCfA",
      "visitas": "22428757",
      "fecha": "06/05/1990"
    },
    {
      "url": "https://120minutes.org/video/041590/midnight+oil+dead+heart",
      "name": "Midnight Oil | Dead Heart",
      "youtubeUrl": "https://www.youtube.com/watch?v=16bFBzx7I_0",
      "youtubeId": "16bFBzx7I_0",
      "visitas": "21958327",
      "fecha": "15/04/1990"
    },
    {
      "url": "https://120minutes.org/video/012190/erasure+blue+savannah",
      "name": "Erasure | Blue Savannah",
      "youtubeUrl": "https://www.youtube.com/watch?v=HZPQtb6NWKM",
      "youtubeId": "HZPQtb6NWKM",
      "visitas": "21935095",
      "fecha": "21/01/1990"
    },
    {
      "url": "https://120minutes.org/video/122390/the+cure+fascination+street",
      "name": "The Cure | Fascination Street",
      "youtubeUrl": "https://www.youtube.com/watch?v=7ZsQdLlvuk4",
      "youtubeId": "7ZsQdLlvuk4",
      "visitas": "21631484",
      "fecha": "23/12/1990"
    },
    {
      "url": "https://120minutes.org/video/071590/social+distortion+ball+and+chain",
      "name": "Social Distortion | Ball And Chain",
      "youtubeUrl": "https://www.youtube.com/watch?v=_NWjehpGSO0",
      "youtubeId": "_NWjehpGSO0",
      "visitas": "20577022",
      "fecha": "15/07/1990"
    },
    {
      "url": "https://120minutes.org/video/041590/peter+murphy+cuts+you+up",
      "name": "Peter Murphy | Cuts You Up",
      "youtubeUrl": "https://www.youtube.com/watch?v=UrfFHzqGBZI",
      "youtubeId": "UrfFHzqGBZI",
      "visitas": "19634032",
      "fecha": "15/04/1990"
    },
    {
      "url": "https://120minutes.org/video/052090/joy+division+atmosphere",
      "name": "Joy Division | Atmosphere",
      "youtubeUrl": "https://www.youtube.com/watch?v=1EdUjlawLJM",
      "youtubeId": "1EdUjlawLJM",
      "visitas": "19399582",
      "fecha": "20/05/1990"
    },
    {
      "url": "https://120minutes.org/video/102190/the+charlatans+uk+the+only+one+i+know",
      "name": "The Charlatans U.K. | The Only One I Know",
      "youtubeUrl": "https://www.youtube.com/watch?v=0RJwW77Lsj8",
      "youtubeId": "0RJwW77Lsj8",
      "visitas": "15333105",
      "fecha": "21/10/1990"
    },
    {
      "url": "https://120minutes.org/video/061790/the+stone+roses+fools+gold",
      "name": "The Stone Roses | Fools Gold",
      "youtubeUrl": "https://www.youtube.com/watch?v=NSD11dnphg0",
      "youtubeId": "NSD11dnphg0",
      "visitas": "15210861",
      "fecha": "17/06/1990"
    },
    {
      "url": "https://120minutes.org/video/123090/janes+addiction+been+caught+stealing",
      "name": "Jane's Addiction | Been Caught Stealing",
      "youtubeUrl": "https://www.youtube.com/watch?v=jrwjiO1MCVs",
      "youtubeId": "jrwjiO1MCVs",
      "visitas": "14302029",
      "fecha": "30/12/1990"
    },
    {
      "url": "https://120minutes.org/video/112590/elvis+costello+olivers+army",
      "name": "Elvis Costello | Oliver's Army",
      "youtubeUrl": "https://www.youtube.com/watch?v=LrjHz5hrupA",
      "youtubeId": "LrjHz5hrupA",
      "visitas": "13842073",
      "fecha": "25/11/1990"
    },
    {
      "url": "https://120minutes.org/video/052790/tom+tom+club+genius+of+love",
      "name": "Tom Tom Club | Genius of Love",
      "youtubeUrl": "https://www.youtube.com/watch?v=aCWCF19nUhA",
      "youtubeId": "aCWCF19nUhA",
      "visitas": "13258830",
      "fecha": "27/05/1990"
    },
    {
      "url": "https://120minutes.org/video/040890/midnight+oil+blue+sky+mine",
      "name": "Midnight Oil | Blue Sky Mine",
      "youtubeUrl": "https://www.youtube.com/watch?v=Ofrqm6-LCqs",
      "youtubeId": "Ofrqm6-LCqs",
      "visitas": "13170230",
      "fecha": "08/04/1990"
    },
    {
      "url": "https://120minutes.org/video/050690/the+jesus+and+mary+chain+just+like+honey",
      "name": "The Jesus and Mary Chain | Just Like Honey",
      "youtubeUrl": "https://www.youtube.com/watch?v=7EgB__YratE",
      "youtubeId": "7EgB__YratE",
      "visitas": "12476771",
      "fecha": "06/05/1990"
    },
    {
      "url": "https://120minutes.org/video/102190/primus+john+the+fisherman",
      "name": "Primus | John the Fisherman",
      "youtubeUrl": "https://www.youtube.com/watch?v=lkFMJ4-ai1I",
      "youtubeId": "lkFMJ4-ai1I",
      "visitas": "12442306",
      "fecha": "21/10/1990"
    },
    {
      "url": "https://120minutes.org/video/042290/yaz+nobodys+diary",
      "name": "Yaz | Nobody's Diary",
      "youtubeUrl": "https://www.youtube.com/watch?v=1qq7jTPkjVg",
      "youtubeId": "1qq7jTPkjVg",
      "visitas": "12344106",
      "fecha": "22/04/1990"
    },
    {
      "url": "https://120minutes.org/video/123090/morrissey+last+of+the+famous+international+playboys",
      "name": "Morrissey | Last Of The Famous International Playboys",
      "youtubeUrl": "https://www.youtube.com/watch?v=Bk1wUKoXL20",
      "youtubeId": "Bk1wUKoXL20",
      "visitas": "11337353",
      "fecha": "30/12/1990"
    },
    {
      "url": "https://120minutes.org/video/050690/the+smiths+girlfriend+in+a+coma",
      "name": "The Smiths | Girlfriend in a Coma",
      "youtubeUrl": "https://www.youtube.com/watch?v=3GhoWZ5qTwI",
      "youtubeId": "3GhoWZ5qTwI",
      "visitas": "10872589",
      "fecha": "06/05/1990"
    },
    {
      "url": "https://120minutes.org/video/123090/siouxsie+the+banshees+the+passenger",
      "name": "Siouxsie & The Banshees | The Passenger",
      "youtubeUrl": "https://www.youtube.com/watch?v=4nAON-MwUPY",
      "youtubeId": "4nAON-MwUPY",
      "visitas": "10235445",
      "fecha": "30/12/1990"
    },
    {
      "url": "https://120minutes.org/video/090990/sonic+youth+kool+thing",
      "name": "Sonic Youth | Kool Thing",
      "youtubeUrl": "https://www.youtube.com/watch?v=SDTSUwIZdMk",
      "youtubeId": "SDTSUwIZdMk",
      "visitas": "10073165",
      "fecha": "09/09/1990"
    },
    {
      "url": "https://120minutes.org/video/090990/prefab+sprout+when+love+breaks+down",
      "name": "Prefab Sprout | When Love Breaks Down",
      "youtubeUrl": "https://www.youtube.com/watch?v=QeZkLV3ZjeI",
      "youtubeId": "QeZkLV3ZjeI",
      "visitas": "10024737",
      "fecha": "09/09/1990"
    },
    {
      "url": "https://120minutes.org/video/042290/electronic+getting+away+with+it",
      "name": "Electronic | Getting Away With It",
      "youtubeUrl": "https://www.youtube.com/watch?v=DSfjtdnUsls",
      "youtubeId": "DSfjtdnUsls",
      "visitas": "9326418",
      "fecha": "22/04/1990"
    },
    {
      "url": "https://120minutes.org/video/012190/janes+addiction+mountain+song",
      "name": "Jane's Addiction | Mountain Song",
      "youtubeUrl": "https://www.youtube.com/watch?v=1kAIMlISHhU",
      "youtubeId": "1kAIMlISHhU",
      "visitas": "9319411",
      "fecha": "21/01/1990"
    },
    {
      "url": "https://120minutes.org/video/122390/the+cure+the+caterpillar",
      "name": "The Cure | The Caterpillar",
      "youtubeUrl": "https://www.youtube.com/watch?v=nzxJ5YvYfx4",
      "youtubeId": "nzxJ5YvYfx4",
      "visitas": "9201310",
      "fecha": "23/12/1990"
    },
    {
      "url": "https://120minutes.org/video/112590/public+image+ltd+rise",
      "name": "Public Image Ltd. | Rise",
      "youtubeUrl": "https://www.youtube.com/watch?v=Vq7JSic1DtM",
      "youtubeId": "Vq7JSic1DtM",
      "visitas": "9076176",
      "fecha": "25/11/1990"
    },
    {
      "url": "https://120minutes.org/video/012190/kate+bush+the+sensual+world",
      "name": "Kate Bush | The Sensual World",
      "youtubeUrl": "https://www.youtube.com/watch?v=h1DDndY0FLI",
      "youtubeId": "h1DDndY0FLI",
      "visitas": "8812546",
      "fecha": "21/01/1990"
    },
    {
      "url": "https://120minutes.org/video/091690/charlotte+sometimes+the+cure",
      "name": "Charlotte Sometimes  | The Cure",
      "youtubeUrl": "https://www.youtube.com/watch?v=4KeII31qyck",
      "youtubeId": "4KeII31qyck",
      "visitas": "8699712",
      "fecha": "16/09/1990"
    },
    {
      "url": "https://120minutes.org/video/123090/happy+mondays+kinky+afro",
      "name": "Happy Mondays | Kinky Afro",
      "youtubeUrl": "https://www.youtube.com/watch?v=O8maBsuhHr4",
      "youtubeId": "O8maBsuhHr4",
      "visitas": "8522859",
      "fecha": "30/12/1990"
    },
    {
      "url": "https://120minutes.org/video/123090/cocteau+twins+heaven+or+las+vegas",
      "name": "Cocteau Twins | Heaven Or Las Vegas",
      "youtubeUrl": "https://www.youtube.com/watch?v=6KnYw4EwYGc",
      "youtubeId": "6KnYw4EwYGc",
      "visitas": "8192863",
      "fecha": "30/12/1990"
    },
    {
      "url": "https://120minutes.org/video/071590/happy+mondays+step+on",
      "name": "Happy Mondays | Step On",
      "youtubeUrl": "https://www.youtube.com/watch?v=mFBQ0PH5rM4",
      "youtubeId": "mFBQ0PH5rM4",
      "visitas": "8143985",
      "fecha": "15/07/1990"
    },
    {
      "url": "https://120minutes.org/video/120290/david+bowie+jean+genie",
      "name": "David Bowie | Jean Genie",
      "youtubeUrl": "https://www.youtube.com/watch?v=kMYg_Ra4cr8",
      "youtubeId": "kMYg_Ra4cr8",
      "visitas": "7929028",
      "fecha": "02/12/1990"
    },
    {
      "url": "https://120minutes.org/video/042290/pixies+monkey+gone+to+heaven",
      "name": "Pixies | Monkey Gone to Heaven",
      "youtubeUrl": "https://www.youtube.com/watch?v=EHC9HE7vazI",
      "youtubeId": "EHC9HE7vazI",
      "visitas": "7614181",
      "fecha": "22/04/1990"
    },
    {
      "url": "https://120minutes.org/video/010790/the+jesus+mary+chain+head+on",
      "name": "The Jesus & Mary Chain | Head On",
      "youtubeUrl": "https://www.youtube.com/watch?v=eGp47YwDZ48",
      "youtubeId": "eGp47YwDZ48",
      "visitas": "7497066",
      "fecha": "07/01/1990"
    },
    {
      "url": "https://120minutes.org/video/090990/the+cure+primary",
      "name": "The Cure | Primary",
      "youtubeUrl": "https://www.youtube.com/watch?v=0xrZ61cuKLk",
      "youtubeId": "0xrZ61cuKLk",
      "visitas": "7482302",
      "fecha": "09/09/1990"
    },
    {
      "url": "https://120minutes.org/video/122390/the+cure+why+cant+i+be+you",
      "name": "The Cure | Why Can't I Be You?",
      "youtubeUrl": "https://www.youtube.com/watch?v=MI0a9hTh5AU",
      "youtubeId": "MI0a9hTh5AU",
      "visitas": "7047195",
      "fecha": "23/12/1990"
    },
    {
      "url": "https://120minutes.org/video/061790/the+cure+lets+go+to+bed",
      "name": "The Cure | Let's Go To Bed",
      "youtubeUrl": "https://www.youtube.com/watch?v=j6vVP91C3Iw",
      "youtubeId": "j6vVP91C3Iw",
      "visitas": "6742526",
      "fecha": "17/06/1990"
    },
    {
      "url": "https://120minutes.org/video/090290/janes+addiction+stop",
      "name": "Jane's Addiction | Stop",
      "youtubeUrl": "https://www.youtube.com/watch?v=ZwI02OHtZTg",
      "youtubeId": "ZwI02OHtZTg",
      "visitas": "6647410",
      "fecha": "02/09/1990"
    },
    {
      "url": "https://120minutes.org/video/042290/bauhaus+bela+lugosis+dead",
      "name": "Bauhaus | Bela Lugosi's Dead",
      "youtubeUrl": "https://www.youtube.com/watch?v=Yy9h2q_dr9k",
      "youtubeId": "Yy9h2q_dr9k",
      "visitas": "6587219",
      "fecha": "22/04/1990"
    },
    {
      "url": "https://120minutes.org/video/051390/midnight+oil+forgotten+years",
      "name": "Midnight Oil | Forgotten Years",
      "youtubeUrl": "https://www.youtube.com/watch?v=X9eap_cKLP4",
      "youtubeId": "X9eap_cKLP4",
      "visitas": "6387056",
      "fecha": "13/05/1990"
    },
    {
      "url": "https://120minutes.org/video/012190/rem+fall+on+me",
      "name": "R.E.M. | Fall On Me",
      "youtubeUrl": "https://www.youtube.com/watch?v=lf6vCjtaV1k",
      "youtubeId": "lf6vCjtaV1k",
      "visitas": "5677176",
      "fecha": "21/01/1990"
    },
    {
      "url": "https://120minutes.org/video/123090/new+order+round+and+round",
      "name": "New Order | Round And Round",
      "youtubeUrl": "https://www.youtube.com/watch?v=t1tjQqWqqAA",
      "youtubeId": "t1tjQqWqqAA",
      "visitas": "5606550",
      "fecha": "30/12/1990"
    },
    {
      "url": "https://120minutes.org/video/091690/crash+the+primitives",
      "name": "Crash  | The Primitives",
      "youtubeUrl": "https://www.youtube.com/watch?v=1y7NGqfZteg",
      "youtubeId": "1y7NGqfZteg",
      "visitas": "5395535",
      "fecha": "16/09/1990"
    },
    {
      "url": "https://120minutes.org/video/010790/ministry+stigmata",
      "name": "Ministry | Stigmata",
      "youtubeUrl": "https://www.youtube.com/watch?v=qxaPj19VnRA",
      "youtubeId": "qxaPj19VnRA",
      "visitas": "5387871",
      "fecha": "07/01/1990"
    },
    {
      "url": "https://120minutes.org/video/082690/midnight+oil+king+of+the+mountain",
      "name": "Midnight Oil | King Of The Mountain",
      "youtubeUrl": "https://www.youtube.com/watch?v=OuC_k51NUqU",
      "youtubeId": "OuC_k51NUqU",
      "visitas": "5352328",
      "fecha": "26/08/1990"
    },
    {
      "url": "https://120minutes.org/video/091690/down+in+it+nine+inch+nails",
      "name": "Down In It  | Nine Inch Nails",
      "youtubeUrl": "https://www.youtube.com/watch?v=QrrEo3hZABU",
      "youtubeId": "QrrEo3hZABU",
      "visitas": "4903132",
      "fecha": "16/09/1990"
    },
    {
      "url": "https://120minutes.org/video/120290/bauhaus+ziggy+stardust",
      "name": "Bauhaus | Ziggy Stardust",
      "youtubeUrl": "https://www.youtube.com/watch?v=rhJZrRV5YKo",
      "youtubeId": "rhJZrRV5YKo",
      "visitas": "4756251",
      "fecha": "02/12/1990"
    },
    {
      "url": "https://120minutes.org/video/100790/pixies+velouria",
      "name": "Pixies | Velouria",
      "youtubeUrl": "https://www.youtube.com/watch?v=nc0Mv4Iyxvc",
      "youtubeId": "nc0Mv4Iyxvc",
      "visitas": "4634598",
      "fecha": "07/10/1990"
    },
    {
      "url": "https://120minutes.org/video/051390/the+lightning+seeds+pure",
      "name": "The Lightning Seeds | Pure",
      "youtubeUrl": "https://www.youtube.com/watch?v=lbqMD7YrGGQ",
      "youtubeId": "lbqMD7YrGGQ",
      "visitas": "4415154",
      "fecha": "13/05/1990"
    },
    {
      "url": "https://120minutes.org/video/123090/drivin+n+cryin+fly+me+courageous",
      "name": "Drivin' N' Cryin' | Fly Me Courageous",
      "youtubeUrl": "https://www.youtube.com/watch?v=W6kplh51lPg",
      "youtubeId": "W6kplh51lPg",
      "visitas": "4325606",
      "fecha": "30/12/1990"
    },
    {
      "url": "https://120minutes.org/video/122390/the+cure+the+walk",
      "name": "The Cure | The Walk",
      "youtubeUrl": "https://www.youtube.com/watch?v=gkCYh1x44G8",
      "youtubeId": "gkCYh1x44G8",
      "visitas": "4155479",
      "fecha": "23/12/1990"
    },
    {
      "url": "https://120minutes.org/video/050690/echo+the+bunnymen+seven+seas",
      "name": "Echo & The Bunnymen | Seven Seas",
      "youtubeUrl": "https://www.youtube.com/watch?v=LbYxP11rbSM",
      "youtubeId": "LbYxP11rbSM",
      "visitas": "3995723",
      "fecha": "06/05/1990"
    },
    {
      "url": "https://120minutes.org/video/091690/i+against+i+bad+brains",
      "name": "I Against I  | Bad Brains",
      "youtubeUrl": "https://www.youtube.com/watch?v=cCEkuo94X6I",
      "youtubeId": "cCEkuo94X6I",
      "visitas": "3791304",
      "fecha": "16/09/1990"
    },
    {
      "url": "https://120minutes.org/video/061790/they+might+be+giants+istanbul+not+constantinople",
      "name": "They Might Be Giants | Istanbul (Not Constantinople)",
      "youtubeUrl": "https://www.youtube.com/watch?v=0XlO39kCQ-8",
      "youtubeId": "0XlO39kCQ-8",
      "visitas": "3569597",
      "fecha": "17/06/1990"
    },
    {
      "url": "https://120minutes.org/video/102190/primal+scream+loaded",
      "name": "Primal Scream | Loaded",
      "youtubeUrl": "https://www.youtube.com/watch?v=Y3ixEzKA4k0",
      "youtubeId": "Y3ixEzKA4k0",
      "visitas": "3551745",
      "fecha": "21/10/1990"
    },
    {
      "url": "https://120minutes.org/video/090990/cocteau+twins+iceblink+luck",
      "name": "Cocteau Twins | Iceblink Luck",
      "youtubeUrl": "https://www.youtube.com/watch?v=L_Tj4bJ0VFw",
      "youtubeId": "L_Tj4bJ0VFw",
      "visitas": "3280890",
      "fecha": "09/09/1990"
    },
    {
      "url": "https://120minutes.org/video/042290/the+smiths+sheila+take+a+bow",
      "name": "The Smiths | Sheila Take a Bow",
      "youtubeUrl": "https://www.youtube.com/watch?v=q-8kKH4COvg",
      "youtubeId": "q-8kKH4COvg",
      "visitas": "3236576",
      "fecha": "22/04/1990"
    },
    {
      "url": "https://120minutes.org/video/091690/type+everything+is+possible+living+colour",
      "name": "Type (Everything Is Possible) | Living Colour",
      "youtubeUrl": "https://www.youtube.com/watch?v=1HbF3EAt3ck",
      "youtubeId": "1HbF3EAt3ck",
      "visitas": "3193459",
      "fecha": "16/09/1990"
    },
    {
      "url": "https://120minutes.org/video/122390/the+cure+hot+hot+hot%21%21%21",
      "name": "The Cure | Hot Hot Hot!!!",
      "youtubeUrl": "https://www.youtube.com/watch?v=p0E9urVs-2o",
      "youtubeId": "p0E9urVs-2o",
      "visitas": "3087558",
      "fecha": "23/12/1990"
    },
    {
      "url": "https://120minutes.org/video/111190/concrete+blonde+caroline",
      "name": "Concrete Blonde | Caroline",
      "youtubeUrl": "https://www.youtube.com/watch?v=wlg91FG9m5Y",
      "youtubeId": "wlg91FG9m5Y",
      "visitas": "3028496",
      "fecha": "11/11/1990"
    },
    {
      "url": "https://120minutes.org/video/123090/rem+radio+free+europe",
      "name": "R.E.M. | Radio Free Europe",
      "youtubeUrl": "https://www.youtube.com/watch?v=Ac0oaXhz1u8",
      "youtubeId": "Ac0oaXhz1u8",
      "visitas": "2762611",
      "fecha": "30/12/1990"
    },
    {
      "url": "https://120minutes.org/video/112590/lush+sweetness+and+light",
      "name": "Lush | Sweetness And Light",
      "youtubeUrl": "https://www.youtube.com/watch?v=u7cqkpy4QrQ",
      "youtubeId": "u7cqkpy4QrQ",
      "visitas": "2721333",
      "fecha": "25/11/1990"
    },
    {
      "url": "https://120minutes.org/video/042990/the+damned+alone+again+or",
      "name": "The Damned | Alone Again Or",
      "youtubeUrl": "https://www.youtube.com/watch?v=nYVDN27CrOo",
      "youtubeId": "nYVDN27CrOo",
      "visitas": "2556641",
      "fecha": "29/04/1990"
    },
    {
      "url": "https://120minutes.org/video/120290/they+might+be+giants+birdhouse+in+your+soul",
      "name": "They Might Be Giants | Birdhouse In Your Soul",
      "youtubeUrl": "https://www.youtube.com/watch?v=vn_or9gEB6g",
      "youtubeId": "vn_or9gEB6g",
      "visitas": "2524952",
      "fecha": "02/12/1990"
    },
    {
      "url": "https://120minutes.org/video/100790/the+cure+the+hanging+garden",
      "name": "The Cure | The Hanging Garden",
      "youtubeUrl": "https://www.youtube.com/watch?v=yEH5jReEkSk",
      "youtubeId": "yEH5jReEkSk",
      "visitas": "2412297",
      "fecha": "07/10/1990"
    },
    {
      "url": "https://120minutes.org/video/111190/soup+dragons+im+free",
      "name": "Soup Dragons | I'm Free",
      "youtubeUrl": "https://www.youtube.com/watch?v=EVw7fzIP6cQ",
      "youtubeId": "EVw7fzIP6cQ",
      "visitas": "2406427",
      "fecha": "11/11/1990"
    },
    {
      "url": "https://120minutes.org/video/102190/the+cure+never+enough",
      "name": "The Cure | Never Enough",
      "youtubeUrl": "https://www.youtube.com/watch?v=l5Cqp3pnE98",
      "youtubeId": "l5Cqp3pnE98",
      "visitas": "2347629",
      "fecha": "21/10/1990"
    },
    {
      "url": "https://120minutes.org/video/050690/morrissey+ouija+board+ouija+board",
      "name": "Morrissey | Ouija Board, Ouija Board",
      "youtubeUrl": "https://www.youtube.com/watch?v=T8V82TXOzm0",
      "youtubeId": "T8V82TXOzm0",
      "visitas": "2276353",
      "fecha": "06/05/1990"
    },
    {
      "url": "https://120minutes.org/video/012190/drivin+n+cryin+honeysuckle+blue",
      "name": "Drivin' N' Cryin' | Honeysuckle Blue",
      "youtubeUrl": "https://www.youtube.com/watch?v=h_3CvrKWQe0",
      "youtubeId": "h_3CvrKWQe0",
      "visitas": "1995554",
      "fecha": "21/01/1990"
    },
    {
      "url": "https://120minutes.org/video/010790/husker+du+dont+want+to+know+if+you+are+lonely",
      "name": "Husker Du | Don't Want To Know If You Are Lonely",
      "youtubeUrl": "https://www.youtube.com/watch?v=eoKeH7JYE48",
      "youtubeId": "eoKeH7JYE48",
      "visitas": "1960079",
      "fecha": "07/01/1990"
    },
    {
      "url": "https://120minutes.org/video/123090/sinead+oconnor+mandinka",
      "name": "Sinead O'Connor | Mandinka",
      "youtubeUrl": "https://www.youtube.com/watch?v=Gf_RHVjPrHY",
      "youtubeId": "Gf_RHVjPrHY",
      "visitas": "1870436",
      "fecha": "30/12/1990"
    },
    {
      "url": "https://120minutes.org/video/060390/the+ramones+i+believe+in+miracles",
      "name": "The Ramones | I Believe in Miracles",
      "youtubeUrl": "https://www.youtube.com/watch?v=V1VczvVrD_I",
      "youtubeId": "V1VczvVrD_I",
      "visitas": "1767237",
      "fecha": "03/06/1990"
    },
    {
      "url": "https://120minutes.org/video/042290/depeche+mode+the+meaning+of+love",
      "name": "Depeche Mode | The Meaning of Love",
      "youtubeUrl": "https://www.youtube.com/watch?v=Fkc6TYIxNls",
      "youtubeId": "Fkc6TYIxNls",
      "visitas": "1503838",
      "fecha": "22/04/1990"
    },
    {
      "url": "https://120minutes.org/video/052790/the+ramones+something+to+believe+in",
      "name": "The Ramones | Something To Believe In",
      "youtubeUrl": "https://www.youtube.com/watch?v=Whz_VoCS858",
      "youtubeId": "Whz_VoCS858",
      "visitas": "1402821",
      "fecha": "27/05/1990"
    },
    {
      "url": "https://120minutes.org/video/042990/public+image+limited+seattle",
      "name": "Public Image Limited | Seattle",
      "youtubeUrl": "https://www.youtube.com/watch?v=bFOjktDN0IA",
      "youtubeId": "bFOjktDN0IA",
      "visitas": "1391380",
      "fecha": "29/04/1990"
    },
    {
      "url": "https://120minutes.org/video/071590/iggy+pop+home",
      "name": "Iggy Pop | Home",
      "youtubeUrl": "https://www.youtube.com/watch?v=0A9binTPMKU",
      "youtubeId": "0A9binTPMKU",
      "visitas": "1353185",
      "fecha": "15/07/1990"
    },
    {
      "url": "https://120minutes.org/video/102890/love+and+rockets+ball+of+confusion",
      "name": "Love and Rockets | Ball of Confusion",
      "youtubeUrl": "https://www.youtube.com/watch?v=NcfXWtI7ML0",
      "youtubeId": "NcfXWtI7ML0",
      "visitas": "1345784",
      "fecha": "28/10/1990"
    },
    {
      "url": "https://120minutes.org/video/102190/public+image+ltd+disappointed",
      "name": "Public Image Ltd. | Disappointed",
      "youtubeUrl": "https://www.youtube.com/watch?v=b6Bv887-JlM",
      "youtubeId": "b6Bv887-JlM",
      "visitas": "1309719",
      "fecha": "21/10/1990"
    },
    {
      "url": "https://120minutes.org/video/090290/dramarama+anything+anything",
      "name": "Dramarama | Anything Anything",
      "youtubeUrl": "https://www.youtube.com/watch?v=yFhx6FLxGxQ",
      "youtubeId": "yFhx6FLxGxQ",
      "visitas": "1303383",
      "fecha": "02/09/1990"
    },
    {
      "url": "https://120minutes.org/video/082690/dinosaur+jr+just+like+heaven",
      "name": "Dinosaur Jr. | Just Like Heaven",
      "youtubeUrl": "https://www.youtube.com/watch?v=UT7IpRx08tE",
      "youtubeId": "UT7IpRx08tE",
      "visitas": "1237385",
      "fecha": "26/08/1990"
    },
    {
      "url": "https://120minutes.org/video/082690/concrete+blonde+everybody+knows",
      "name": "Concrete Blonde | Everybody Knows",
      "youtubeUrl": "https://www.youtube.com/watch?v=l5Fb4K8pNmg",
      "youtubeId": "l5Fb4K8pNmg",
      "visitas": "1234870",
      "fecha": "26/08/1990"
    },
    {
      "url": "https://120minutes.org/video/091690/deeper+shade+of+soul+urban+dance+squad",
      "name": "Deeper Shade of Soul  | Urban Dance Squad",
      "youtubeUrl": "https://www.youtube.com/watch?v=K4Dw6q-5iaA",
      "youtubeId": "K4Dw6q-5iaA",
      "visitas": "1231851",
      "fecha": "16/09/1990"
    },
    {
      "url": "https://120minutes.org/video/042990/red+hot+chili+peppers+knock+me+down",
      "name": "Red Hot Chili Peppers | Knock Me Down",
      "youtubeUrl": "https://www.youtube.com/watch?v=STHllreT1Vk",
      "youtubeId": "STHllreT1Vk",
      "visitas": "1191010",
      "fecha": "29/04/1990"
    },
    {
      "url": "https://120minutes.org/video/100790/the+sundays+cant+be+sure",
      "name": "The Sundays | Can't Be Sure",
      "youtubeUrl": "https://www.youtube.com/watch?v=yARVs1ZNLjU",
      "youtubeId": "yARVs1ZNLjU",
      "visitas": "1166121",
      "fecha": "07/10/1990"
    },
    {
      "url": "https://120minutes.org/video/052790/the+ramones+i+believe+in+miracles",
      "name": "The Ramones | I Believe in Miracles",
      "youtubeUrl": "https://www.youtube.com/watch?v=QCee-vToE_M",
      "youtubeId": "QCee-vToE_M",
      "visitas": "1141287",
      "fecha": "27/05/1990"
    },
    {
      "url": "https://120minutes.org/video/060390/red+hot+chili+peppers+show+me+your+soul",
      "name": "Red Hot Chili Peppers | Show Me Your Soul",
      "youtubeUrl": "https://www.youtube.com/watch?v=XAqSmB1-ecY",
      "youtubeId": "XAqSmB1-ecY",
      "visitas": "1129278",
      "fecha": "03/06/1990"
    },
    {
      "url": "https://120minutes.org/video/042990/lloyd+cole+perfect+skin",
      "name": "Lloyd Cole | Perfect Skin",
      "youtubeUrl": "https://www.youtube.com/watch?v=DDoJQH8Pz8s",
      "youtubeId": "DDoJQH8Pz8s",
      "visitas": "1122981",
      "fecha": "29/04/1990"
    },
    {
      "url": "https://120minutes.org/video/051390/front+242+quite+unusual",
      "name": "Front 242 | Quite Unusual",
      "youtubeUrl": "https://www.youtube.com/watch?v=urd8tG0xvoM",
      "youtubeId": "urd8tG0xvoM",
      "visitas": "1121038",
      "fecha": "13/05/1990"
    },
    {
      "url": "https://120minutes.org/video/102890/aztec+camera+good+morning+britain",
      "name": "Aztec Camera | Good Morning Britain",
      "youtubeUrl": "https://www.youtube.com/watch?v=3_QSMTtUQYY",
      "youtubeId": "3_QSMTtUQYY",
      "visitas": "1035395",
      "fecha": "28/10/1990"
    },
    {
      "url": "https://120minutes.org/video/050690/world+party+ship+of+fools",
      "name": "World Party | Ship of Fools",
      "youtubeUrl": "https://www.youtube.com/watch?v=B2nCugGQZO0",
      "youtubeId": "B2nCugGQZO0",
      "visitas": "957689",
      "fecha": "06/05/1990"
    },
    {
      "url": "https://120minutes.org/video/112590/sonic+youth+disappearer",
      "name": "Sonic Youth | Disappearer",
      "youtubeUrl": "https://www.youtube.com/watch?v=Y8MFqJ22kSs",
      "youtubeId": "Y8MFqJ22kSs",
      "visitas": "934513",
      "fecha": "25/11/1990"
    },
    {
      "url": "https://120minutes.org/video/090990/the+hoodoo+gurus+come+anytime",
      "name": "The Hoodoo Gurus | Come Anytime",
      "youtubeUrl": "https://www.youtube.com/watch?v=_BWEoUYUAtA",
      "youtubeId": "_BWEoUYUAtA",
      "visitas": "907722",
      "fecha": "09/09/1990"
    },
    {
      "url": "https://120minutes.org/video/082690/dread+zeppelin+heartbreaker+at+the+end+of+a+lonely+street",
      "name": "Dread Zeppelin  | Heartbreaker (At The End Of A Lonely Street)",
      "youtubeUrl": "https://www.youtube.com/watch?v=rAM1MKi7bNU",
      "youtubeId": "rAM1MKi7bNU",
      "visitas": "889768",
      "fecha": "26/08/1990"
    },
    {
      "url": "https://120minutes.org/video/090990/the+pogues+white+city",
      "name": "The Pogues | White City",
      "youtubeUrl": "https://www.youtube.com/watch?v=BJIoDTcPGds",
      "youtubeId": "BJIoDTcPGds",
      "visitas": "864130",
      "fecha": "09/09/1990"
    },
    {
      "url": "https://120minutes.org/video/052090/the+wedding+present+kennedy",
      "name": "The Wedding Present | Kennedy",
      "youtubeUrl": "https://www.youtube.com/watch?v=PuNYyNqCSSg",
      "youtubeId": "PuNYyNqCSSg",
      "visitas": "826087",
      "fecha": "20/05/1990"
    },
    {
      "url": "https://120minutes.org/video/090290/bob+mould+see+a+little+light",
      "name": "Bob Mould | See A Little Light",
      "youtubeUrl": "https://www.youtube.com/watch?v=dDnNr6lNxvc",
      "youtubeId": "dDnNr6lNxvc",
      "visitas": "786191",
      "fecha": "02/09/1990"
    },
    {
      "url": "https://120minutes.org/video/042290/lush+deluxe",
      "name": "Lush | Deluxe",
      "youtubeUrl": "https://www.youtube.com/watch?v=aKrw5wOlSng",
      "youtubeId": "aKrw5wOlSng",
      "visitas": "762686",
      "fecha": "22/04/1990"
    },
    {
      "url": "https://120minutes.org/video/122390/the+cure+close+to+me+closer+mix",
      "name": "The Cure | Close To Me (Closer Mix)",
      "youtubeUrl": "https://www.youtube.com/watch?v=phMX4DBafG4",
      "youtubeId": "phMX4DBafG4",
      "visitas": "746223",
      "fecha": "23/12/1990"
    },
    {
      "url": "https://120minutes.org/video/111190/alien+sex+fiend+now+im+feeling+zombified",
      "name": "Alien Sex Fiend | Now I'm Feeling Zombified",
      "youtubeUrl": "https://www.youtube.com/watch?v=Bfm7cOJfOjk",
      "youtubeId": "Bfm7cOJfOjk",
      "visitas": "733555",
      "fecha": "11/11/1990"
    },
    {
      "url": "https://120minutes.org/video/090290/the+stone+roses+one+love",
      "name": "The Stone Roses | One Love",
      "youtubeUrl": "https://www.youtube.com/watch?v=60qyfdcAOGE",
      "youtubeId": "60qyfdcAOGE",
      "visitas": "689100",
      "fecha": "02/09/1990"
    },
    {
      "url": "https://120minutes.org/video/102890/public+image+ltd+dont+ask+me",
      "name": "Public Image Ltd. | Don't Ask Me",
      "youtubeUrl": "https://www.youtube.com/watch?v=NJZe_AVtD2c",
      "youtubeId": "NJZe_AVtD2c",
      "visitas": "684956",
      "fecha": "28/10/1990"
    },
    {
      "url": "https://120minutes.org/video/042990/world+party+way+down+now",
      "name": "World Party | Way Down Now",
      "youtubeUrl": "https://www.youtube.com/watch?v=ZZrIdbumFiI",
      "youtubeId": "ZZrIdbumFiI",
      "visitas": "649260",
      "fecha": "29/04/1990"
    },
    {
      "url": "https://120minutes.org/video/040890/del+amitri+kiss+this+thing+goodbye",
      "name": "del Amitri | Kiss This Thing Goodbye",
      "youtubeUrl": "https://www.youtube.com/watch?v=Ify_f6XoqMU",
      "youtubeId": "Ify_f6XoqMU",
      "visitas": "641711",
      "fecha": "08/04/1990"
    },
    {
      "url": "https://120minutes.org/video/123090/ride+like+a+daydream",
      "name": "Ride | Like A Daydream",
      "youtubeUrl": "https://www.youtube.com/watch?v=8zzo25t_eC8",
      "youtubeId": "8zzo25t_eC8",
      "visitas": "623339",
      "fecha": "30/12/1990"
    },
    {
      "url": "https://120minutes.org/video/010790/david+byrne+make+believe+mambo",
      "name": "David Byrne | Make Believe Mambo",
      "youtubeUrl": "https://www.youtube.com/watch?v=wiruARgmQ34",
      "youtubeId": "wiruARgmQ34",
      "visitas": "614704",
      "fecha": "07/01/1990"
    },
    {
      "url": "https://120minutes.org/video/100790/james+how+was+it+for+you",
      "name": "James | How Was It For You",
      "youtubeUrl": "https://www.youtube.com/watch?v=Lm0IBdp6Y1A",
      "youtubeId": "Lm0IBdp6Y1A",
      "visitas": "611298",
      "fecha": "07/10/1990"
    },
    {
      "url": "https://120minutes.org/video/012190/pop+will+eat+itself+can+u+dig+it",
      "name": "Pop Will Eat Itself | Can U Dig It?",
      "youtubeUrl": "https://www.youtube.com/watch?v=36nWNAvtwrw",
      "youtubeId": "36nWNAvtwrw",
      "visitas": "609911",
      "fecha": "21/01/1990"
    },
    {
      "url": "https://120minutes.org/video/071590/iggy+pop+cry+for+love",
      "name": "Iggy Pop | Cry For Love",
      "youtubeUrl": "https://www.youtube.com/watch?v=wI9vzh7CZIw",
      "youtubeId": "wI9vzh7CZIw",
      "visitas": "600156",
      "fecha": "15/07/1990"
    },
    {
      "url": "https://120minutes.org/video/052090/happy+mondays+hallelujah",
      "name": "Happy Mondays | Hallelujah",
      "youtubeUrl": "https://www.youtube.com/watch?v=dAk6Euat-6A",
      "youtubeId": "dAk6Euat-6A",
      "visitas": "540597",
      "fecha": "20/05/1990"
    },
    {
      "url": "https://120minutes.org/video/060390/the+mission+uk+butterfly+on+a+wheel",
      "name": "The Mission U.K. | Butterfly on a Wheel",
      "youtubeUrl": "https://www.youtube.com/watch?v=OKRACt6PpYY",
      "youtubeId": "OKRACt6PpYY",
      "visitas": "537227",
      "fecha": "03/06/1990"
    },
    {
      "url": "https://120minutes.org/video/060390/the+sundays+heres+where+the+story+ends",
      "name": "The Sundays | Here's Where the Story Ends",
      "youtubeUrl": "https://www.youtube.com/watch?v=2HV5KfE4xMA",
      "youtubeId": "2HV5KfE4xMA",
      "visitas": "509813",
      "fecha": "03/06/1990"
    },
    {
      "url": "https://120minutes.org/video/042290/the+church+metropolis",
      "name": "The Church | Metropolis",
      "youtubeUrl": "https://www.youtube.com/watch?v=96YYp98ye9o",
      "youtubeId": "96YYp98ye9o",
      "visitas": "490062",
      "fecha": "22/04/1990"
    },
    {
      "url": "https://120minutes.org/video/123090/goo+goo+dolls+there+you+are",
      "name": "Goo Goo Dolls | There You Are",
      "youtubeUrl": "https://www.youtube.com/watch?v=ojMgn8UwUAQ",
      "youtubeId": "ojMgn8UwUAQ",
      "visitas": "479283",
      "fecha": "30/12/1990"
    },
    {
      "url": "https://120minutes.org/video/052090/soul+asylum+cartoon",
      "name": "Soul Asylum | Cartoon",
      "youtubeUrl": "https://www.youtube.com/watch?v=9IAF5Q6S79I",
      "youtubeId": "9IAF5Q6S79I",
      "visitas": "476829",
      "fecha": "20/05/1990"
    },
    {
      "url": "https://120minutes.org/video/102190/the+replacements+merry+go+round",
      "name": "The Replacements | Merry Go Round",
      "youtubeUrl": "https://www.youtube.com/watch?v=uac_KQn9Q-M",
      "youtubeId": "uac_KQn9Q-M",
      "visitas": "468775",
      "fecha": "21/10/1990"
    },
    {
      "url": "https://120minutes.org/video/041590/nitzer+ebb+lightning+man",
      "name": "Nitzer Ebb | Lightning Man",
      "youtubeUrl": "https://www.youtube.com/watch?v=AHkD6NO2dmM",
      "youtubeId": "AHkD6NO2dmM",
      "visitas": "466696",
      "fecha": "15/04/1990"
    },
    {
      "url": "https://120minutes.org/video/102190/iggy+pop+butt+town",
      "name": "Iggy Pop | Butt Town",
      "youtubeUrl": "https://www.youtube.com/watch?v=X08Y38927xI",
      "youtubeId": "X08Y38927xI",
      "visitas": "466062",
      "fecha": "21/10/1990"
    },
    {
      "url": "https://120minutes.org/video/091690/lets+all+go+to+the+fire+dances+killing+joke",
      "name": "Let's All Go (To The Fire Dances)  | Killing Joke",
      "youtubeUrl": "https://www.youtube.com/watch?v=GUQhNEyAf0I",
      "youtubeId": "GUQhNEyAf0I",
      "visitas": "465694",
      "fecha": "16/09/1990"
    },
    {
      "url": "https://120minutes.org/video/082690/jellyfish+the+king+is+half+undressed",
      "name": "Jellyfish | The King Is Half-Undressed",
      "youtubeUrl": "https://www.youtube.com/watch?v=AgdgptaBma8",
      "youtubeId": "AgdgptaBma8",
      "visitas": "454380",
      "fecha": "26/08/1990"
    },
    {
      "url": "https://120minutes.org/video/060390/fishbone+party+at+ground+zero",
      "name": "Fishbone | Party at Ground Zero",
      "youtubeUrl": "https://www.youtube.com/watch?v=MJCaFe1yamg",
      "youtubeId": "MJCaFe1yamg",
      "visitas": "431702",
      "fecha": "03/06/1990"
    },
    {
      "url": "https://120minutes.org/video/082690/the+railway+children+every+beat+of+the+heart",
      "name": "The Railway Children | Every Beat Of The Heart",
      "youtubeUrl": "https://www.youtube.com/watch?v=nDpOMTjE-bg",
      "youtubeId": "nDpOMTjE-bg",
      "visitas": "395280",
      "fecha": "26/08/1990"
    },
    {
      "url": "https://120minutes.org/video/052090/morrissey+november+spawned+a+monster",
      "name": "Morrissey | November Spawned a Monster",
      "youtubeUrl": "https://www.youtube.com/watch?v=TndBViTADMI",
      "youtubeId": "TndBViTADMI",
      "visitas": "395018",
      "fecha": "20/05/1990"
    },
    {
      "url": "https://120minutes.org/video/112590/rem+get+up",
      "name": "R.E.M. | Get Up",
      "youtubeUrl": "https://www.youtube.com/watch?v=rPIEBohSojI",
      "youtubeId": "rPIEBohSojI",
      "visitas": "376049",
      "fecha": "25/11/1990"
    },
    {
      "url": "https://120minutes.org/video/081990/nitzer+ebb+fun+to+be+had",
      "name": "Nitzer Ebb | Fun To Be Had",
      "youtubeUrl": "https://www.youtube.com/watch?v=e99Pv5rOv5Y",
      "youtubeId": "e99Pv5rOv5Y",
      "visitas": "370572",
      "fecha": "19/08/1990"
    },
    {
      "url": "https://120minutes.org/video/071590/world+party+put+the+message+in+the+box",
      "name": "World Party | Put The Message In The Box",
      "youtubeUrl": "https://www.youtube.com/watch?v=udCaa-Ju3dk",
      "youtubeId": "udCaa-Ju3dk",
      "visitas": "367066",
      "fecha": "15/07/1990"
    },
    {
      "url": "https://120minutes.org/video/050690/the+fall+victoria",
      "name": "The Fall | Victoria",
      "youtubeUrl": "https://www.youtube.com/watch?v=N0I2u6DKnwI",
      "youtubeId": "N0I2u6DKnwI",
      "visitas": "363477",
      "fecha": "06/05/1990"
    },
    {
      "url": "https://120minutes.org/video/061790/the+pogues+yeah+yeah+yeah+yeah+yeah",
      "name": "The Pogues | Yeah Yeah Yeah Yeah Yeah",
      "youtubeUrl": "https://www.youtube.com/watch?v=W-JdFM41RUg",
      "youtubeId": "W-JdFM41RUg",
      "visitas": "346653",
      "fecha": "17/06/1990"
    },
    {
      "url": "https://120minutes.org/video/112590/midnight+oil+bedlam+bridge",
      "name": "Midnight Oil | Bedlam Bridge",
      "youtubeUrl": "https://www.youtube.com/watch?v=927kKJlC8tU",
      "youtubeId": "927kKJlC8tU",
      "visitas": "338652",
      "fecha": "25/11/1990"
    },
    {
      "url": "https://120minutes.org/video/040890/cowboy+junkies+sun+comes+up+its+tuesday+morning",
      "name": "Cowboy Junkies | Sun Comes Up. It's Tuesday Morning",
      "youtubeUrl": "https://www.youtube.com/watch?v=48pFXE28y8Y",
      "youtubeId": "48pFXE28y8Y",
      "visitas": "322743",
      "fecha": "08/04/1990"
    },
    {
      "url": "https://120minutes.org/video/111190/andy+prieboy+tomorrow+wendy",
      "name": "Andy Prieboy | Tomorrow Wendy",
      "youtubeUrl": "https://www.youtube.com/watch?v=zZBQGCI2hm0",
      "youtubeId": "zZBQGCI2hm0",
      "visitas": "320662",
      "fecha": "11/11/1990"
    },
    {
      "url": "https://120minutes.org/video/012190/love+and+rockets+mirror+people",
      "name": "Love And Rockets | Mirror People",
      "youtubeUrl": "https://www.youtube.com/watch?v=O0uD20h9mbY",
      "youtubeId": "O0uD20h9mbY",
      "visitas": "302588",
      "fecha": "21/01/1990"
    },
    {
      "url": "https://120minutes.org/video/102190/the+connells+stone+cold+yesterday",
      "name": "The Connells | Stone Cold Yesterday",
      "youtubeUrl": "https://www.youtube.com/watch?v=zvbZ3lsT5nw",
      "youtubeId": "zvbZ3lsT5nw",
      "visitas": "300764",
      "fecha": "21/10/1990"
    },
    {
      "url": "https://120minutes.org/video/052090/psychedelic+furs+dumb+waiter",
      "name": "Psychedelic Furs | Dumb Waiter",
      "youtubeUrl": "https://www.youtube.com/watch?v=mrX9Mg4ersQ",
      "youtubeId": "mrX9Mg4ersQ",
      "visitas": "292109",
      "fecha": "20/05/1990"
    },
    {
      "url": "https://120minutes.org/video/091690/the+summer+yo+la+tengo",
      "name": "The Summer  | Yo La Tengo",
      "youtubeUrl": "https://www.youtube.com/watch?v=hu9DnE7gTIU",
      "youtubeId": "hu9DnE7gTIU",
      "visitas": "285464",
      "fecha": "16/09/1990"
    },
    {
      "url": "https://120minutes.org/video/050690/jesus+and+mary+chain+her+way+of+praying",
      "name": "Jesus and Mary Chain | Her Way of Praying",
      "youtubeUrl": "https://www.youtube.com/watch?v=K7gRQH7R2NQ",
      "youtubeId": "K7gRQH7R2NQ",
      "visitas": "285174",
      "fecha": "06/05/1990"
    },
    {
      "url": "https://120minutes.org/video/040890/the+mission+uk+deliverance",
      "name": "The Mission U.K. | Deliverance",
      "youtubeUrl": "https://www.youtube.com/watch?v=Uvna9LYvzm0",
      "youtubeId": "Uvna9LYvzm0",
      "visitas": "269492",
      "fecha": "08/04/1990"
    },
    {
      "url": "https://120minutes.org/video/040890/house+of+love+i+dont+know+why+i+love+you",
      "name": "House of Love | I Don't Know Why I Love You",
      "youtubeUrl": "https://www.youtube.com/watch?v=XpBr24xW2Q8",
      "youtubeId": "XpBr24xW2Q8",
      "visitas": "255784",
      "fecha": "08/04/1990"
    },
    {
      "url": "https://120minutes.org/video/102190/the+posies+golden+blunders",
      "name": "The Posies | Golden Blunders",
      "youtubeUrl": "https://www.youtube.com/watch?v=7onIN6IwIeQ",
      "youtubeId": "7onIN6IwIeQ",
      "visitas": "243848",
      "fecha": "21/10/1990"
    },
    {
      "url": "https://120minutes.org/video/102190/inspiral+carpets+commercial+rain",
      "name": "Inspiral Carpets | Commercial Rain",
      "youtubeUrl": "https://www.youtube.com/watch?v=OtiAllw_Eiw",
      "youtubeId": "OtiAllw_Eiw",
      "visitas": "239264",
      "fecha": "21/10/1990"
    },
    {
      "url": "https://120minutes.org/video/102190/redd+kross+annies+gone",
      "name": "Redd Kross | Annie's Gone",
      "youtubeUrl": "https://www.youtube.com/watch?v=nmtbEK7Q4uA",
      "youtubeId": "nmtbEK7Q4uA",
      "visitas": "228566",
      "fecha": "21/10/1990"
    },
    {
      "url": "https://120minutes.org/video/051390/dramarama+last+cigarette",
      "name": "Dramarama | Last Cigarette",
      "youtubeUrl": "https://www.youtube.com/watch?v=VT3EL_0QaqI",
      "youtubeId": "VT3EL_0QaqI",
      "visitas": "219521",
      "fecha": "13/05/1990"
    },
    {
      "url": "https://120minutes.org/video/081990/the+sisters+of+mercy+dominion",
      "name": "The Sisters Of Mercy | Dominion",
      "youtubeUrl": "https://www.youtube.com/watch?v=4FrxFYfNNe0",
      "youtubeId": "4FrxFYfNNe0",
      "visitas": "218338",
      "fecha": "19/08/1990"
    },
    {
      "url": "https://120minutes.org/video/112590/frontline+assembly+iceolate",
      "name": "Frontline Assembly | Iceolate",
      "youtubeUrl": "https://www.youtube.com/watch?v=40TRQYxohmA",
      "youtubeId": "40TRQYxohmA",
      "visitas": "214445",
      "fecha": "25/11/1990"
    },
    {
      "url": "https://120minutes.org/video/102890/an+emotional+fish+celebrate",
      "name": "An Emotional Fish | Celebrate",
      "youtubeUrl": "https://www.youtube.com/watch?v=n3oQgAFBfWU",
      "youtubeId": "n3oQgAFBfWU",
      "visitas": "212808",
      "fecha": "28/10/1990"
    },
    {
      "url": "https://120minutes.org/video/120990/soul+asylum+easy+street",
      "name": "Soul Asylum  | Easy Street",
      "youtubeUrl": "https://www.youtube.com/watch?v=aCcAf78LoX4",
      "youtubeId": "aCcAf78LoX4",
      "visitas": "206527",
      "fecha": "09/12/1990"
    },
    {
      "url": "https://120minutes.org/video/071590/aztec+camera+the+crying+scene",
      "name": "Aztec Camera | The Crying Scene",
      "youtubeUrl": "https://www.youtube.com/watch?v=9aQXcT71cw4",
      "youtubeId": "9aQXcT71cw4",
      "visitas": "201561",
      "fecha": "15/07/1990"
    },
    {
      "url": "https://120minutes.org/video/010790/the+wonder+stuff+dont+let+me+down",
      "name": "The Wonder Stuff | Don't Let Me Down",
      "youtubeUrl": "https://www.youtube.com/watch?v=SIKUZjc4gVo",
      "youtubeId": "SIKUZjc4gVo",
      "visitas": "197332",
      "fecha": "07/01/1990"
    },
    {
      "url": "https://120minutes.org/video/051390/hunters+and+collectors+when+the+river+runs+dry",
      "name": "Hunters And Collectors | When The River Runs Dry",
      "youtubeUrl": "https://www.youtube.com/watch?v=Jzt8kNoSLdY",
      "youtubeId": "Jzt8kNoSLdY",
      "visitas": "196462",
      "fecha": "13/05/1990"
    },
    {
      "url": "https://120minutes.org/video/041590/sinead+oconnor+jump+into+the+river",
      "name": "Sinead O'Connor | Jump into the River",
      "youtubeUrl": "https://www.youtube.com/watch?v=1ORbUdApLhk",
      "youtubeId": "1ORbUdApLhk",
      "visitas": "195724",
      "fecha": "15/04/1990"
    },
    {
      "url": "https://120minutes.org/video/040890/psychedelic+furs+house",
      "name": "Psychedelic Furs | House",
      "youtubeUrl": "https://www.youtube.com/watch?v=xZjTwh-WGBo",
      "youtubeId": "xZjTwh-WGBo",
      "visitas": "192937",
      "fecha": "08/04/1990"
    },
    {
      "url": "https://120minutes.org/video/071590/iggy+pop+cold+metal",
      "name": "Iggy Pop | Cold Metal",
      "youtubeUrl": "https://www.youtube.com/watch?v=mLnL1-7lvVE",
      "youtubeId": "mLnL1-7lvVE",
      "visitas": "181214",
      "fecha": "15/07/1990"
    },
    {
      "url": "https://120minutes.org/video/040890/toad+the+wet+sprocket+come+back+down",
      "name": "Toad The Wet Sprocket | Come Back Down",
      "youtubeUrl": "https://www.youtube.com/watch?v=uCYH2pGf-Ws",
      "youtubeId": "uCYH2pGf-Ws",
      "visitas": "180417",
      "fecha": "08/04/1990"
    },
    {
      "url": "https://120minutes.org/video/081990/the+boomtown+rats+up+all+night",
      "name": "The Boomtown Rats | Up All Night",
      "youtubeUrl": "https://www.youtube.com/watch?v=GStr1ZHxlDI",
      "youtubeId": "GStr1ZHxlDI",
      "visitas": "174537",
      "fecha": "19/08/1990"
    },
    {
      "url": "https://120minutes.org/video/042990/mc+900+ft+jesus+truth+is+out+of+style",
      "name": "MC 900 Ft Jesus | Truth Is Out Of Style",
      "youtubeUrl": "https://www.youtube.com/watch?v=8vgDpI8kU98",
      "youtubeId": "8vgDpI8kU98",
      "visitas": "168215",
      "fecha": "29/04/1990"
    },
    {
      "url": "https://120minutes.org/video/042990/lloyd+cole+downtown",
      "name": "Lloyd Cole | Downtown",
      "youtubeUrl": "https://www.youtube.com/watch?v=7lRFKIue6Hg",
      "youtubeId": "7lRFKIue6Hg",
      "visitas": "167488",
      "fecha": "29/04/1990"
    },
    {
      "url": "https://120minutes.org/video/040890/renegade+soundwave+probably+a+robbery",
      "name": "Renegade Soundwave | Probably a Robbery",
      "youtubeUrl": "https://www.youtube.com/watch?v=AIKYTUmGtCk",
      "youtubeId": "AIKYTUmGtCk",
      "visitas": "164259",
      "fecha": "08/04/1990"
    },
    {
      "url": "https://120minutes.org/video/111190/ultra+vivid+scene+special+one",
      "name": "Ultra Vivid Scene | Special One",
      "youtubeUrl": "https://www.youtube.com/watch?v=1DCjSShu_VA",
      "youtubeId": "1DCjSShu_VA",
      "visitas": "152008",
      "fecha": "11/11/1990"
    },
    {
      "url": "https://120minutes.org/video/052790/jerry+harrison%3A+casual+gods+rev+it+up",
      "name": "Jerry Harrison: Casual Gods | Rev It Up",
      "youtubeUrl": "https://www.youtube.com/watch?v=CdzW93F-aHg",
      "youtubeId": "CdzW93F-aHg",
      "visitas": "147354",
      "fecha": "27/05/1990"
    },
    {
      "url": "https://120minutes.org/video/012190/lords+of+the+new+church+russian+roulette",
      "name": "Lords Of The New Church | Russian Roulette",
      "youtubeUrl": "https://www.youtube.com/watch?v=g83z7G9tVMA",
      "youtubeId": "g83z7G9tVMA",
      "visitas": "134994",
      "fecha": "21/01/1990"
    },
    {
      "url": "https://120minutes.org/video/120290/front+242+tragedy+for+you",
      "name": "Front 242 | Tragedy For You",
      "youtubeUrl": "https://www.youtube.com/watch?v=z6OUDGl1zyQ",
      "youtubeId": "z6OUDGl1zyQ",
      "visitas": "133550",
      "fecha": "02/12/1990"
    },
    {
      "url": "https://120minutes.org/video/042290/the+silencers+razor+blades+of+love",
      "name": "The Silencers | Razor Blades of Love",
      "youtubeUrl": "https://www.youtube.com/watch?v=2SvNP2poXz0",
      "youtubeId": "2SvNP2poXz0",
      "visitas": "127980",
      "fecha": "22/04/1990"
    },
    {
      "url": "https://120minutes.org/video/041590/the+creatures+fury+eyes",
      "name": "The Creatures | Fury Eyes",
      "youtubeUrl": "https://www.youtube.com/watch?v=KNini9H24MU",
      "youtubeId": "KNini9H24MU",
      "visitas": "120607",
      "fecha": "15/04/1990"
    },
    {
      "url": "https://120minutes.org/video/091690/its+too+late+bob+mould",
      "name": "It's Too Late  | Bob Mould",
      "youtubeUrl": "https://www.youtube.com/watch?v=Y-fPibdYPJM",
      "youtubeId": "Y-fPibdYPJM",
      "visitas": "120135",
      "fecha": "16/09/1990"
    },
    {
      "url": "https://120minutes.org/video/041590/galaxie+500+blue+thunder",
      "name": "Galaxie 500 | Blue Thunder",
      "youtubeUrl": "https://www.youtube.com/watch?v=lc3kxjy2GNk",
      "youtubeId": "lc3kxjy2GNk",
      "visitas": "118348",
      "fecha": "15/04/1990"
    },
    {
      "url": "https://120minutes.org/video/042990/that+petrol+emotion+hey+venus",
      "name": "That Petrol Emotion | Hey Venus",
      "youtubeUrl": "https://www.youtube.com/watch?v=Y156vSPDGOc",
      "youtubeId": "Y156vSPDGOc",
      "visitas": "112583",
      "fecha": "29/04/1990"
    },
    {
      "url": "https://120minutes.org/video/102890/lemonheads+half+the+time",
      "name": "Lemonheads | Half the Time",
      "youtubeUrl": "https://www.youtube.com/watch?v=n4zVYRBHPyM",
      "youtubeId": "n4zVYRBHPyM",
      "visitas": "109197",
      "fecha": "28/10/1990"
    },
    {
      "url": "https://120minutes.org/video/102190/robyn+hitchcock+the+egyptians+madonna+of+the+wasps",
      "name": "Robyn Hitchcock & the Egyptians | Madonna of the Wasps",
      "youtubeUrl": "https://www.youtube.com/watch?v=3J_1Fs9_J_A",
      "youtubeId": "3J_1Fs9_J_A",
      "visitas": "108867",
      "fecha": "21/10/1990"
    },
    {
      "url": "https://120minutes.org/video/061790/the+fall+telephone+thing",
      "name": "The Fall | Telephone Thing",
      "youtubeUrl": "https://www.youtube.com/watch?v=60wQc6bzjCk",
      "youtubeId": "60wQc6bzjCk",
      "visitas": "103756",
      "fecha": "17/06/1990"
    },
    {
      "url": "https://120minutes.org/video/050690/ministry+revenge",
      "name": "Ministry | Revenge",
      "youtubeUrl": "https://www.youtube.com/watch?v=y_RZJk9I1mo",
      "youtubeId": "y_RZJk9I1mo",
      "visitas": "102714",
      "fecha": "06/05/1990"
    },
    {
      "url": "https://120minutes.org/video/050690/the+church+tantalized",
      "name": "The Church | Tantalized",
      "youtubeUrl": "https://www.youtube.com/watch?v=4rsHbPF8HKs",
      "youtubeId": "4rsHbPF8HKs",
      "visitas": "93679",
      "fecha": "06/05/1990"
    },
    {
      "url": "https://120minutes.org/video/111190/gene+loves+jezebel+tangled+up+in+you",
      "name": "Gene Loves Jezebel | Tangled Up in You",
      "youtubeUrl": "https://www.youtube.com/watch?v=hBe6aPm1Lw8",
      "youtubeId": "hBe6aPm1Lw8",
      "visitas": "92148",
      "fecha": "11/11/1990"
    },
    {
      "url": "https://120minutes.org/video/102890/darling+buds+crystal+clear",
      "name": "Darling Buds | Crystal Clear",
      "youtubeUrl": "https://www.youtube.com/watch?v=Z8PuE0bo4P8",
      "youtubeId": "Z8PuE0bo4P8",
      "visitas": "85472",
      "fecha": "28/10/1990"
    },
    {
      "url": "https://120minutes.org/video/042990/grant+hart+all+of+my+senses",
      "name": "Grant Hart | All of My Senses",
      "youtubeUrl": "https://www.youtube.com/watch?v=4JFtmMF4UIc",
      "youtubeId": "4JFtmMF4UIc",
      "visitas": "83637",
      "fecha": "29/04/1990"
    },
    {
      "url": "https://120minutes.org/video/081990/devo+post+postmodern+man",
      "name": "Devo | Post-Postmodern Man",
      "youtubeUrl": "https://www.youtube.com/watch?v=jCJoe_4eYU4",
      "youtubeId": "jCJoe_4eYU4",
      "visitas": "83523",
      "fecha": "19/08/1990"
    },
    {
      "url": "https://120minutes.org/video/042290/poi+dog+pondering+u+li+la+lu",
      "name": "Poi Dog Pondering | U Li La Lu",
      "youtubeUrl": "https://www.youtube.com/watch?v=qtmvf5x9Wzc",
      "youtubeId": "qtmvf5x9Wzc",
      "visitas": "81843",
      "fecha": "22/04/1990"
    },
    {
      "url": "https://120minutes.org/video/060390/lou+reed+john+cale+nobody+but+you",
      "name": "Lou Reed/John Cale | Nobody But You",
      "youtubeUrl": "https://www.youtube.com/watch?v=40v_Gu4MeKc",
      "youtubeId": "40v_Gu4MeKc",
      "visitas": "80079",
      "fecha": "03/06/1990"
    },
    {
      "url": "https://120minutes.org/video/060390/the+origin+growing+old",
      "name": "The Origin | Growing Old",
      "youtubeUrl": "https://www.youtube.com/watch?v=dGR84pp9ah8",
      "youtubeId": "dGR84pp9ah8",
      "visitas": "74948",
      "fecha": "03/06/1990"
    },
    {
      "url": "https://120minutes.org/video/042990/die+pretty+true+fools+fall",
      "name": "Die Pretty | True Fools Fall",
      "youtubeUrl": "https://www.youtube.com/watch?v=EZyd775dz9E",
      "youtubeId": "EZyd775dz9E",
      "visitas": "71008",
      "fecha": "29/04/1990"
    },
    {
      "url": "https://120minutes.org/video/091690/dreamtime+the+heart+throbs",
      "name": "Dreamtime  | The Heart Throbs",
      "youtubeUrl": "https://www.youtube.com/watch?v=vzMWJRuLdp8",
      "youtubeId": "vzMWJRuLdp8",
      "visitas": "66932",
      "fecha": "16/09/1990"
    },
    {
      "url": "https://120minutes.org/video/111190/sisters+of+mercy+more",
      "name": "Sisters of Mercy | More",
      "youtubeUrl": "https://www.youtube.com/watch?v=BlVcdXowPvQ",
      "youtubeId": "BlVcdXowPvQ",
      "visitas": "65209",
      "fecha": "11/11/1990"
    },
    {
      "url": "https://120minutes.org/video/102890/the+mekons+ghosts+of+american+astronauts",
      "name": "The Mekons | Ghosts of American Astronauts",
      "youtubeUrl": "https://www.youtube.com/watch?v=JtaAWk6YLqQ",
      "youtubeId": "JtaAWk6YLqQ",
      "visitas": "62571",
      "fecha": "28/10/1990"
    },
    {
      "url": "https://120minutes.org/video/051390/camper+van+beethoven+take+the+skinheads+bowling",
      "name": "Camper Van Beethoven | Take The Skinheads Bowling",
      "youtubeUrl": "https://www.youtube.com/watch?v=DlX1cQU8rxI",
      "youtubeId": "DlX1cQU8rxI",
      "visitas": "59265",
      "fecha": "13/05/1990"
    },
    {
      "url": "https://120minutes.org/video/120990/meat+beat+manifesto+psych+out",
      "name": "Meat Beat Manifesto | Psych-Out",
      "youtubeUrl": "https://www.youtube.com/watch?v=qfH0AOAVDPU",
      "youtubeId": "qfH0AOAVDPU",
      "visitas": "59073",
      "fecha": "09/12/1990"
    },
    {
      "url": "https://120minutes.org/video/041590/tackhead+ticking+time+bomb",
      "name": "Tackhead | Ticking Time Bomb",
      "youtubeUrl": "https://www.youtube.com/watch?v=nN2cZ5andQ0",
      "youtubeId": "nN2cZ5andQ0",
      "visitas": "57732",
      "fecha": "15/04/1990"
    },
    {
      "url": "https://120minutes.org/video/090290/mano+negra+rock+and+roll+band",
      "name": "Mano Negra | Rock And Roll Band",
      "youtubeUrl": "https://www.youtube.com/watch?v=dxfGwFwQ8Vs",
      "youtubeId": "dxfGwFwQ8Vs",
      "visitas": "57158",
      "fecha": "02/09/1990"
    },
    {
      "url": "https://120minutes.org/video/123090/buffalo+tom+birdbrain",
      "name": "Buffalo Tom | Birdbrain",
      "youtubeUrl": "https://www.youtube.com/watch?v=B_Tgb-H0CcY",
      "youtubeId": "B_Tgb-H0CcY",
      "visitas": "55170",
      "fecha": "30/12/1990"
    },
    {
      "url": "https://120minutes.org/video/061790/the+church+the+unguarded+moment",
      "name": "The Church | The Unguarded Moment",
      "youtubeUrl": "https://www.youtube.com/watch?v=dg5DI5yCUZc",
      "youtubeId": "dg5DI5yCUZc",
      "visitas": "54725",
      "fecha": "17/06/1990"
    },
    {
      "url": "https://120minutes.org/video/051390/the+chills+heavenly+pop+hit",
      "name": "The Chills | Heavenly Pop Hit",
      "youtubeUrl": "https://www.youtube.com/watch?v=Hd0Y0SQV610",
      "youtubeId": "Hd0Y0SQV610",
      "visitas": "50303",
      "fecha": "13/05/1990"
    },
    {
      "url": "https://120minutes.org/video/010790/flat+duo+jets+wild+wild+lover",
      "name": "Flat Duo Jets | Wild Wild Lover",
      "youtubeUrl": "https://www.youtube.com/watch?v=fyPxiTRQVVQ",
      "youtubeId": "fyPxiTRQVVQ",
      "visitas": "49926",
      "fecha": "07/01/1990"
    },
    {
      "url": "https://120minutes.org/video/010790/big+audio+dynamite+free+theme+from+flashback",
      "name": "Big Audio Dynamite | Free (Theme From Flashback)",
      "youtubeUrl": "https://www.youtube.com/watch?v=Zk2zR4wfEoU",
      "youtubeId": "Zk2zR4wfEoU",
      "visitas": "48317",
      "fecha": "07/01/1990"
    },
    {
      "url": "https://120minutes.org/video/061790/the+church+youre+still+beautiful",
      "name": "The Church  | You're Still Beautiful",
      "youtubeUrl": "https://www.youtube.com/watch?v=kuk7LhCyreE",
      "youtubeId": "kuk7LhCyreE",
      "visitas": "46657",
      "fecha": "17/06/1990"
    },
    {
      "url": "https://120minutes.org/video/102890/television+personalities+salvador+dalis+garden+party",
      "name": "Television Personalities | Salvador Dali's Garden Party",
      "youtubeUrl": "https://www.youtube.com/watch?v=QWrdMETPe1I",
      "youtubeId": "QWrdMETPe1I",
      "visitas": "45749",
      "fecha": "28/10/1990"
    },
    {
      "url": "https://120minutes.org/video/051390/the+silos+im+over+you",
      "name": "The Silos | I'm Over You",
      "youtubeUrl": "https://www.youtube.com/watch?v=Askfkq5w7Zs",
      "youtubeId": "Askfkq5w7Zs",
      "visitas": "43190",
      "fecha": "13/05/1990"
    },
    {
      "url": "https://120minutes.org/video/090290/trip+shakespeare+pearle",
      "name": "Trip Shakespeare  | Pearle",
      "youtubeUrl": "https://www.youtube.com/watch?v=4lfMjQoHmAA",
      "youtubeId": "4lfMjQoHmAA",
      "visitas": "41689",
      "fecha": "02/09/1990"
    },
    {
      "url": "https://120minutes.org/video/061790/chickasaw+mudd+puppies+mcintosh",
      "name": "Chickasaw Mudd Puppies | Mcintosh",
      "youtubeUrl": "https://www.youtube.com/watch?v=WTvDEQtalMA",
      "youtubeId": "WTvDEQtalMA",
      "visitas": "39344",
      "fecha": "17/06/1990"
    },
    {
      "url": "https://120minutes.org/video/071590/david+j+ill+be+your+chauffer",
      "name": "David J | I'll Be Your Chauffer",
      "youtubeUrl": "https://www.youtube.com/watch?v=Mn9xNWjuPSs",
      "youtubeId": "Mn9xNWjuPSs",
      "visitas": "38362",
      "fecha": "15/07/1990"
    },
    {
      "url": "https://120minutes.org/video/120990/daniel+ash+this+love",
      "name": "Daniel Ash | This Love",
      "youtubeUrl": "https://www.youtube.com/watch?v=rSApZCZMmj4",
      "youtubeId": "rSApZCZMmj4",
      "visitas": "35424",
      "fecha": "09/12/1990"
    },
    {
      "url": "https://120minutes.org/video/061790/adrian+belew+pretty+pink+rose",
      "name": "Adrian Belew | Pretty Pink Rose",
      "youtubeUrl": "https://www.youtube.com/watch?v=xkCrULytNXo",
      "youtubeId": "xkCrULytNXo",
      "visitas": "33071",
      "fecha": "17/06/1990"
    },
    {
      "url": "https://120minutes.org/video/082690/thee+hypnotics+half+man+half+boy",
      "name": "Thee Hypnotics | Half Man, Half Boy",
      "youtubeUrl": "https://www.youtube.com/watch?v=6Qu5FNUlv18",
      "youtubeId": "6Qu5FNUlv18",
      "visitas": "32786",
      "fecha": "26/08/1990"
    },
    {
      "url": "https://120minutes.org/video/081990/dave+stewart+the+spiritual+cowboys+party+town",
      "name": "Dave Stewart & The Spiritual Cowboys | Party Town",
      "youtubeUrl": "https://www.youtube.com/watch?v=rU8bCOItg_E",
      "youtubeId": "rU8bCOItg_E",
      "visitas": "32296",
      "fecha": "19/08/1990"
    },
    {
      "url": "https://120minutes.org/video/040890/the+cramps+bikini+girls+with+machine+guns",
      "name": "The Cramps | Bikini Girls with Machine Guns",
      "youtubeUrl": "https://www.youtube.com/watch?v=qMy9_-mqTw8",
      "youtubeId": "qMy9_-mqTw8",
      "visitas": "31045",
      "fecha": "08/04/1990"
    },
    {
      "url": "https://120minutes.org/video/041590/the+blue+aeroplanes+jacket+hangs",
      "name": "The Blue Aeroplanes | Jacket Hangs",
      "youtubeUrl": "https://www.youtube.com/watch?v=QML9akZ8a7A",
      "youtubeId": "QML9akZ8a7A",
      "visitas": "30033",
      "fecha": "15/04/1990"
    },
    {
      "url": "https://120minutes.org/video/090990/the+cavedogs+leave+me+alone",
      "name": "The Cavedogs  | Leave Me Alone",
      "youtubeUrl": "https://www.youtube.com/watch?v=7LPks6qJYAE",
      "youtubeId": "7LPks6qJYAE",
      "visitas": "29871",
      "fecha": "09/09/1990"
    },
    {
      "url": "https://120minutes.org/video/111190/pixies+dig+for+fire+allison",
      "name": "Pixies | Dig for Fire / Allison",
      "youtubeUrl": "https://www.youtube.com/watch?v=tA96j5l2lvA",
      "youtubeId": "tA96j5l2lvA",
      "visitas": "29762",
      "fecha": "11/11/1990"
    },
    {
      "url": "https://120minutes.org/video/060390/kirsty+maccoll+free+world",
      "name": "Kirsty MacColl | Free World",
      "youtubeUrl": "https://www.youtube.com/watch?v=46gRoPQ8i9A",
      "youtubeId": "46gRoPQ8i9A",
      "visitas": "29403",
      "fecha": "03/06/1990"
    },
    {
      "url": "https://120minutes.org/video/012190/pete+shelley+homosapien",
      "name": "Pete Shelley | Homosapien",
      "youtubeUrl": "https://www.youtube.com/watch?v=lQa1dGk--xI",
      "youtubeId": "lQa1dGk--xI",
      "visitas": "27104",
      "fecha": "21/01/1990"
    },
    {
      "url": "https://120minutes.org/video/123090/danielle+dax+tomorrow+never+knows",
      "name": "Danielle Dax | Tomorrow Never Knows",
      "youtubeUrl": "https://www.youtube.com/watch?v=CYYqv5YP5TI",
      "youtubeId": "CYYqv5YP5TI",
      "visitas": "26821",
      "fecha": "30/12/1990"
    },
    {
      "url": "https://120minutes.org/video/081990/green+on+red+you+couldnt+get+arrested",
      "name": "Green On Red | You Couldn't Get Arrested",
      "youtubeUrl": "https://www.youtube.com/watch?v=ze47T4GxuD0",
      "youtubeId": "ze47T4GxuD0",
      "visitas": "25461",
      "fecha": "19/08/1990"
    },
    {
      "url": "https://120minutes.org/video/042990/thee+hypnotics+justice+in+freedom",
      "name": "Thee Hypnotics | Justice in Freedom",
      "youtubeUrl": "https://www.youtube.com/watch?v=mQn7jUazYco",
      "youtubeId": "mQn7jUazYco",
      "visitas": "25083",
      "fecha": "29/04/1990"
    },
    {
      "url": "https://120minutes.org/video/123090/john+wesley+harding+if+you+have+ghosts",
      "name": "John Wesley Harding | If You Have Ghosts",
      "youtubeUrl": "https://www.youtube.com/watch?v=Y-koDVehbsY",
      "youtubeId": "Y-koDVehbsY",
      "visitas": "24360",
      "fecha": "30/12/1990"
    },
    {
      "url": "https://120minutes.org/video/120990/the+mission+uk+hands+across+the+ocean",
      "name": "The Mission UK | Hands Across The Ocean",
      "youtubeUrl": "https://www.youtube.com/watch?v=pU5z_AfQz5I",
      "youtubeId": "pU5z_AfQz5I",
      "visitas": "22040",
      "fecha": "09/12/1990"
    },
    {
      "url": "https://120minutes.org/video/120990/the+alarm+unsafe+building",
      "name": "The Alarm | Unsafe Building",
      "youtubeUrl": "https://www.youtube.com/watch?v=J9FBSqw3lqw",
      "youtubeId": "J9FBSqw3lqw",
      "visitas": "21620",
      "fecha": "09/12/1990"
    },
    {
      "url": "https://120minutes.org/video/010790/screaming+blue+messiahs+four+engines+burning",
      "name": "Screaming Blue Messiahs | Four Engines Burning",
      "youtubeUrl": "https://www.youtube.com/watch?v=Y5ftXhWrNaw",
      "youtubeId": "Y5ftXhWrNaw",
      "visitas": "21351",
      "fecha": "07/01/1990"
    },
    {
      "url": "https://120minutes.org/video/051390/john+wesley+harding+the+devil+in+me",
      "name": "John Wesley Harding | The Devil In Me",
      "youtubeUrl": "https://www.youtube.com/watch?v=1pYCdaWQZh8",
      "youtubeId": "1pYCdaWQZh8",
      "visitas": "20583",
      "fecha": "13/05/1990"
    },
    {
      "url": "https://120minutes.org/video/102890/railway+children+music+stop",
      "name": "Railway Children | Music Stop",
      "youtubeUrl": "https://www.youtube.com/watch?v=qXupXoD6mts",
      "youtubeId": "qXupXoD6mts",
      "visitas": "20184",
      "fecha": "28/10/1990"
    },
    {
      "url": "https://120minutes.org/video/090990/jesus+jones+never+enough",
      "name": "Jesus Jones | Never Enough",
      "youtubeUrl": "https://www.youtube.com/watch?v=GH-I2SG76AM",
      "youtubeId": "GH-I2SG76AM",
      "visitas": "19650",
      "fecha": "09/09/1990"
    },
    {
      "url": "https://120minutes.org/video/061790/hothouse+flowers+give+it+up",
      "name": "Hothouse Flowers | Give It Up",
      "youtubeUrl": "https://www.youtube.com/watch?v=f3p3MZ0HXSk",
      "youtubeId": "f3p3MZ0HXSk",
      "visitas": "17712",
      "fecha": "17/06/1990"
    },
    {
      "url": "https://120minutes.org/video/102890/the+flaming+lips+unconciously+screaming",
      "name": "The Flaming Lips | Unconciously Screaming",
      "youtubeUrl": "https://www.youtube.com/watch?v=8amL8azaPqI",
      "youtubeId": "8amL8azaPqI",
      "visitas": "16936",
      "fecha": "28/10/1990"
    },
    {
      "url": "https://120minutes.org/video/051390/urban+dance+squad+no+kid",
      "name": "Urban Dance Squad | No Kid",
      "youtubeUrl": "https://www.youtube.com/watch?v=rWdn8CL4pSM",
      "youtubeId": "rWdn8CL4pSM",
      "visitas": "16802",
      "fecha": "13/05/1990"
    },
    {
      "url": "https://120minutes.org/video/082690/the+soup+dragons+mother+universe",
      "name": "The Soup Dragons | Mother Universe",
      "youtubeUrl": "https://www.youtube.com/watch?v=EcsOzkpQQZM",
      "youtubeId": "EcsOzkpQQZM",
      "visitas": "16283",
      "fecha": "26/08/1990"
    },
    {
      "url": "https://120minutes.org/video/042290/dramarama+wonderamaland",
      "name": "Dramarama | Wonderamaland",
      "youtubeUrl": "https://www.youtube.com/watch?v=Ih9vmYFzaLs",
      "youtubeId": "Ih9vmYFzaLs",
      "visitas": "16113",
      "fecha": "22/04/1990"
    },
    {
      "url": "https://120minutes.org/video/012190/camper+van+beethoven+i+was+born+in+a+laundromat",
      "name": "Camper Van Beethoven | (I Was Born In A) Laundromat",
      "youtubeUrl": "https://www.youtube.com/watch?v=S04Ie_NmOKo",
      "youtubeId": "S04Ie_NmOKo",
      "visitas": "15888",
      "fecha": "21/01/1990"
    },
    {
      "url": "https://120minutes.org/video/100790/the+lilac+time+all+for+love+and+love+for+all",
      "name": "The Lilac Time | All For Love And Love For All",
      "youtubeUrl": "https://www.youtube.com/watch?v=1-IQ2OKouJU",
      "youtubeId": "1-IQ2OKouJU",
      "visitas": "13014",
      "fecha": "07/10/1990"
    },
    {
      "url": "https://120minutes.org/video/041590/lene+lovich+make+believe",
      "name": "Lene Lovich | Make Believe",
      "youtubeUrl": "https://www.youtube.com/watch?v=9TbRfOHGow4",
      "youtubeId": "9TbRfOHGow4",
      "visitas": "12225",
      "fecha": "15/04/1990"
    },
    {
      "url": "https://120minutes.org/video/050690/ian+mcculloch+candleland",
      "name": "Ian McCulloch | Candleland",
      "youtubeUrl": "https://www.youtube.com/watch?v=oytzwp7rLxg",
      "youtubeId": "oytzwp7rLxg",
      "visitas": "12071",
      "fecha": "06/05/1990"
    },
    {
      "url": "https://120minutes.org/video/112590/the+buck+pets+pearls",
      "name": "The Buck Pets | Pearls",
      "youtubeUrl": "https://www.youtube.com/watch?v=D2mexQNFfDc",
      "youtubeId": "D2mexQNFfDc",
      "visitas": "11717",
      "fecha": "25/11/1990"
    },
    {
      "url": "https://120minutes.org/video/091690/what+now+something+happens",
      "name": "What Now  | Something Happens",
      "youtubeUrl": "https://www.youtube.com/watch?v=PF46voVD7KI",
      "youtubeId": "PF46voVD7KI",
      "visitas": "11390",
      "fecha": "16/09/1990"
    },
    {
      "url": "https://120minutes.org/video/012190/ian+mcculloch+faith+and+healing",
      "name": "Ian McCulloch | Faith And Healing",
      "youtubeUrl": "https://www.youtube.com/watch?v=rnb8AGxCRAI",
      "youtubeId": "rnb8AGxCRAI",
      "visitas": "11275",
      "fecha": "21/01/1990"
    },
    {
      "url": "https://120minutes.org/video/112590/the+trash+can+sinatras+only+tongue+can+tell",
      "name": "The Trash Can Sinatras | Only Tongue Can Tell",
      "youtubeUrl": "https://www.youtube.com/watch?v=0pQenFIFEwo",
      "youtubeId": "0pQenFIFEwo",
      "visitas": "11261",
      "fecha": "25/11/1990"
    },
    {
      "url": "https://120minutes.org/video/012190/the+cynics+girl+youre+on+my+mind",
      "name": "The Cynics | Girl, You're On My Mind",
      "youtubeUrl": "https://www.youtube.com/watch?v=nRsYAhcNPzk",
      "youtubeId": "nRsYAhcNPzk",
      "visitas": "11037",
      "fecha": "21/01/1990"
    },
    {
      "url": "https://120minutes.org/video/102190/galaxie+500+fourth+of+july",
      "name": "Galaxie 500 | Fourth of July",
      "youtubeUrl": "https://www.youtube.com/watch?v=zUD55q_54PE",
      "youtubeId": "zUD55q_54PE",
      "visitas": "10831",
      "fecha": "21/10/1990"
    },
    {
      "url": "https://120minutes.org/video/012190/eleventh+dream+day+testify",
      "name": "Eleventh Dream Day | Testify",
      "youtubeUrl": "https://www.youtube.com/watch?v=FnDSdRmAs74",
      "youtubeId": "FnDSdRmAs74",
      "visitas": "10775",
      "fecha": "21/01/1990"
    },
    {
      "url": "https://120minutes.org/video/050690/robyn+hitchcock+beautiful+girl",
      "name": "Robyn Hitchcock | Beautiful Girl",
      "youtubeUrl": "https://www.youtube.com/watch?v=EYfB4n9Vu4w",
      "youtubeId": "EYfB4n9Vu4w",
      "visitas": "10630",
      "fecha": "06/05/1990"
    },
    {
      "url": "https://120minutes.org/video/082690/24+7+spyz+dont+break+my+heart",
      "name": "24-7 Spyz | Don't Break My Heart",
      "youtubeUrl": "https://www.youtube.com/watch?v=JX2Y95S6kl8",
      "youtubeId": "JX2Y95S6kl8",
      "visitas": "10271",
      "fecha": "26/08/1990"
    },
    {
      "url": "https://120minutes.org/video/041590/gunbunnies+stranded",
      "name": "Gunbunnies | Stranded",
      "youtubeUrl": "https://www.youtube.com/watch?v=e1G0oJJXmmQ",
      "youtubeId": "e1G0oJJXmmQ",
      "visitas": "10197",
      "fecha": "15/04/1990"
    },
    {
      "url": "https://120minutes.org/video/060390/the+blue+aeroplanes+and+swagger",
      "name": "The Blue Aeroplanes | ...And Swagger",
      "youtubeUrl": "https://www.youtube.com/watch?v=f_faCIdDfXs",
      "youtubeId": "f_faCIdDfXs",
      "visitas": "10043",
      "fecha": "03/06/1990"
    },
    {
      "url": "https://120minutes.org/video/052090/ultra+vivid+scene+staring+at+the+sun",
      "name": "Ultra Vivid Scene | Staring at the Sun",
      "youtubeUrl": "https://www.youtube.com/watch?v=HYGJafCEgS4",
      "youtubeId": "HYGJafCEgS4",
      "visitas": "9908",
      "fecha": "20/05/1990"
    },
    {
      "url": "https://120minutes.org/video/041590/loop+arc+lite+sonar",
      "name": "Loop | Arc-lite (Sonar)",
      "youtubeUrl": "https://www.youtube.com/watch?v=KCAmVhcOYr8",
      "youtubeId": "KCAmVhcOYr8",
      "visitas": "9496",
      "fecha": "15/04/1990"
    },
    {
      "url": "https://120minutes.org/video/060390/the+dead+milkmen+methodist+coloring+book",
      "name": "The Dead Milkmen | Methodist Coloring Book",
      "youtubeUrl": "https://www.youtube.com/watch?v=HZPibSWBCqE",
      "youtubeId": "HZPibSWBCqE",
      "visitas": "8622",
      "fecha": "03/06/1990"
    },
    {
      "url": "https://120minutes.org/video/050690/robyn+hitchcock+the+egyptians+heaven",
      "name": "Robyn Hitchcock & The Egyptians | Heaven",
      "youtubeUrl": "https://www.youtube.com/watch?v=RTgXCdUhPjM",
      "youtubeId": "RTgXCdUhPjM",
      "visitas": "8031",
      "fecha": "06/05/1990"
    },
    {
      "url": "https://120minutes.org/video/091690/velouria+live+from+mtv+europe+the+pixies",
      "name": "Velouria (live from MTV Europe)  | The Pixies",
      "youtubeUrl": "https://www.youtube.com/watch?v=61SKtmvAIag",
      "youtubeId": "61SKtmvAIag",
      "visitas": "7762",
      "fecha": "16/09/1990"
    },
    {
      "url": "https://120minutes.org/video/071590/luxuria+jezebel",
      "name": "Luxuria | Jezebel",
      "youtubeUrl": "https://www.youtube.com/watch?v=-qQNsbjz2mU",
      "youtubeId": "-qQNsbjz2mU",
      "visitas": "7095",
      "fecha": "15/07/1990"
    },
    {
      "url": "https://120minutes.org/video/040890/mc+900+ft+jesus+with+dj+zero+im+going+straight+to+heaven",
      "name": "MC 900 Ft Jesus with DJ Zero | I'm Going Straight to Heaven",
      "youtubeUrl": "https://www.youtube.com/watch?v=AUtbhy2oRvk",
      "youtubeId": "AUtbhy2oRvk",
      "visitas": "6295",
      "fecha": "08/04/1990"
    },
    {
      "url": "https://120minutes.org/video/012190/the+del+fuegos+breakaway",
      "name": "The Del Fuegos | Breakaway",
      "youtubeUrl": "https://www.youtube.com/watch?v=YXSSj3lmGyk",
      "youtubeId": "YXSSj3lmGyk",
      "visitas": "6023",
      "fecha": "21/01/1990"
    },
    {
      "url": "https://120minutes.org/video/010790/the+magnolias+pardon+me",
      "name": "The Magnolias | Pardon Me",
      "youtubeUrl": "https://www.youtube.com/watch?v=1cpjLcxSv10",
      "youtubeId": "1cpjLcxSv10",
      "visitas": "5906",
      "fecha": "07/01/1990"
    },
    {
      "url": "https://120minutes.org/video/111190/the+blue+aeroplanes+you+are+loved",
      "name": "The Blue Aeroplanes | You (Are Loved)",
      "youtubeUrl": "https://www.youtube.com/watch?v=c8UJ1HkYy1E",
      "youtubeId": "c8UJ1HkYy1E",
      "visitas": "5455",
      "fecha": "11/11/1990"
    },
    {
      "url": "https://120minutes.org/video/090290/the+jack+rubies+be+with+you",
      "name": "The Jack Rubies | Be With You",
      "youtubeUrl": "https://www.youtube.com/watch?v=ZfcelDaSobg",
      "youtubeId": "ZfcelDaSobg",
      "visitas": "5288",
      "fecha": "02/09/1990"
    },
    {
      "url": "https://120minutes.org/video/120990/urge+overkill+ticket+to+la",
      "name": "Urge Overkill | Ticket To L.A.",
      "youtubeUrl": "https://www.youtube.com/watch?v=CiyOmZ1_FTo",
      "youtubeId": "CiyOmZ1_FTo",
      "visitas": "5267",
      "fecha": "09/12/1990"
    },
    {
      "url": "https://120minutes.org/video/041590/the+walkabouts+ahead+of+the+storm",
      "name": "The Walkabouts | Ahead of the Storm",
      "youtubeUrl": "https://www.youtube.com/watch?v=TH_QNt73Rpw",
      "youtubeId": "TH_QNt73Rpw",
      "visitas": "5248",
      "fecha": "15/04/1990"
    },
    {
      "url": "https://120minutes.org/video/120990/parachute+men+every+other+thursday",
      "name": "Parachute Men | Every Other Thursday",
      "youtubeUrl": "https://www.youtube.com/watch?v=qLpxO2LEois",
      "youtubeId": "qLpxO2LEois",
      "visitas": "4799",
      "fecha": "09/12/1990"
    },
    {
      "url": "https://120minutes.org/video/052090/big+dipper+love+barge",
      "name": "Big Dipper | Love Barge",
      "youtubeUrl": "https://www.youtube.com/watch?v=iPf4sBzM_7M",
      "youtubeId": "iPf4sBzM_7M",
      "visitas": "4746",
      "fecha": "20/05/1990"
    },
    {
      "url": "https://120minutes.org/video/100790/tv+personalities+salvador+dalis+garden+party",
      "name": "TV Personalities | Salvador Dali's Garden Party",
      "youtubeUrl": "https://www.youtube.com/watch?v=w763N6xWSbs",
      "youtubeId": "w763N6xWSbs",
      "visitas": "4458",
      "fecha": "07/10/1990"
    },
    {
      "url": "https://120minutes.org/video/052790/john+doe+lets+be+mad",
      "name": "John Doe | Let's Be Mad",
      "youtubeUrl": "https://www.youtube.com/watch?v=tASzfycajKw",
      "youtubeId": "tASzfycajKw",
      "visitas": "4171",
      "fecha": "27/05/1990"
    },
    {
      "url": "https://120minutes.org/video/010790/hex+ethereal+message",
      "name": "Hex | Ethereal Message",
      "youtubeUrl": "https://www.youtube.com/watch?v=2mxgK-6d7yk",
      "youtubeId": "2mxgK-6d7yk",
      "visitas": "4110",
      "fecha": "07/01/1990"
    },
    {
      "url": "https://120minutes.org/video/051390/john+wesley+harding+here+comes+the+groom",
      "name": "John Wesley Harding | Here Comes The Groom",
      "youtubeUrl": "https://www.youtube.com/watch?v=8S0tX4V5ZuM",
      "youtubeId": "8S0tX4V5ZuM",
      "visitas": "3882",
      "fecha": "13/05/1990"
    },
    {
      "url": "https://120minutes.org/video/082690/the+breeders+hellbound",
      "name": "The Breeders | Hellbound",
      "youtubeUrl": "https://www.youtube.com/watch?v=NrAeLw08XMM",
      "youtubeId": "NrAeLw08XMM",
      "visitas": "3672",
      "fecha": "26/08/1990"
    },
    {
      "url": "https://120minutes.org/video/050690/that+petrol+emotion+cellophane",
      "name": "That Petrol Emotion | Cellophane",
      "youtubeUrl": "https://www.youtube.com/watch?v=DQjick6vEGQ",
      "youtubeId": "DQjick6vEGQ",
      "visitas": "3375",
      "fecha": "06/05/1990"
    },
    {
      "url": "https://120minutes.org/video/090290/the+titanics+mans+inhumanity+to+man",
      "name": "The Titanics | Man's Inhumanity To Man",
      "youtubeUrl": "https://www.youtube.com/watch?v=OnYAvgeH1xg",
      "youtubeId": "OnYAvgeH1xg",
      "visitas": "3243",
      "fecha": "02/09/1990"
    },
    {
      "url": "https://120minutes.org/video/081990/urge+overkill+faroutski",
      "name": "Urge Overkill | Faroutski",
      "youtubeUrl": "https://www.youtube.com/watch?v=pFMLqlUWZnU",
      "youtubeId": "pFMLqlUWZnU",
      "visitas": "3061",
      "fecha": "19/08/1990"
    },
    {
      "url": "https://120minutes.org/video/071590/king+missile+no+point",
      "name": "King Missile | No Point",
      "youtubeUrl": "https://www.youtube.com/watch?v=k0Ua72mn_Ms",
      "youtubeId": "k0Ua72mn_Ms",
      "visitas": "2889",
      "fecha": "15/07/1990"
    },
    {
      "url": "https://120minutes.org/video/112590/pylon+look+alive",
      "name": "Pylon | Look Alive",
      "youtubeUrl": "https://www.youtube.com/watch?v=GsAP90HrmNE",
      "youtubeId": "GsAP90HrmNE",
      "visitas": "2848",
      "fecha": "25/11/1990"
    },
    {
      "url": "https://120minutes.org/video/041590/the+sundays+joy",
      "name": "The Sundays | Joy",
      "youtubeUrl": "https://www.youtube.com/watch?v=XiplF09f2kI",
      "youtubeId": "XiplF09f2kI",
      "visitas": "2595",
      "fecha": "15/04/1990"
    },
    {
      "url": "https://120minutes.org/video/112590/echo+the+bunnymen+enlighten+me",
      "name": "Echo & The Bunnymen | Enlighten Me",
      "youtubeUrl": "https://www.youtube.com/watch?v=a2MJeX3Wq1E",
      "youtubeId": "a2MJeX3Wq1E",
      "visitas": "2544",
      "fecha": "25/11/1990"
    },
    {
      "url": "https://120minutes.org/video/050690/the+fall+telephone+thing",
      "name": "The Fall | Telephone Thing",
      "youtubeUrl": "https://www.youtube.com/watch?v=cdN7BbuL_1c",
      "youtubeId": "cdN7BbuL_1c",
      "visitas": "2526",
      "fecha": "06/05/1990"
    },
    {
      "url": "https://120minutes.org/video/042290/national+peoples+gang+gettin+close+to+god",
      "name": "National People's Gang | Gettin' Close to God",
      "youtubeUrl": "https://www.youtube.com/watch?v=bdSPMMcQZM0",
      "youtubeId": "bdSPMMcQZM0",
      "visitas": "2379",
      "fecha": "22/04/1990"
    },
    {
      "url": "https://120minutes.org/video/052790/something+happens+hello+hello+hello+hello+hello",
      "name": "Something Happens | Hello, Hello, Hello, Hello, Hello",
      "youtubeUrl": "https://www.youtube.com/watch?v=pIBMBgKzEXU",
      "youtubeId": "pIBMBgKzEXU",
      "visitas": "2256",
      "fecha": "27/05/1990"
    },
    {
      "url": "https://120minutes.org/video/052790/deborah+harry+sweet+and+low",
      "name": "Deborah Harry | Sweet and Low",
      "youtubeUrl": "https://www.youtube.com/watch?v=lfythyNpO1Q",
      "youtubeId": "lfythyNpO1Q",
      "visitas": "2158",
      "fecha": "27/05/1990"
    },
    {
      "url": "https://120minutes.org/video/082690/consolidated+dysfunctional+relationship",
      "name": "Consolidated | Dysfunctional Relationship",
      "youtubeUrl": "https://www.youtube.com/watch?v=HUi8qDLaDS8",
      "youtubeId": "HUi8qDLaDS8",
      "visitas": "2095",
      "fecha": "26/08/1990"
    },
    {
      "url": "https://120minutes.org/video/061790/agitpop+forget+me+not",
      "name": "Agitpop | Forget Me Not",
      "youtubeUrl": "https://www.youtube.com/watch?v=Wrlyuk5kqDA",
      "youtubeId": "Wrlyuk5kqDA",
      "visitas": "2024",
      "fecha": "17/06/1990"
    },
    {
      "url": "https://120minutes.org/video/100790/psychefunkapus+we+are+the+young",
      "name": "Psychefunkapus | We Are The Young",
      "youtubeUrl": "https://www.youtube.com/watch?v=W0RlTnOlBHU",
      "youtubeId": "W0RlTnOlBHU",
      "visitas": "1934",
      "fecha": "07/10/1990"
    },
    {
      "url": "https://120minutes.org/video/040890/tall+tales+and+true+passing+out+the+chains",
      "name": "Tall Tales and True | Passing out the Chains",
      "youtubeUrl": "https://www.youtube.com/watch?v=Zb3voAOq8Vk",
      "youtubeId": "Zb3voAOq8Vk",
      "visitas": "1862",
      "fecha": "08/04/1990"
    },
    {
      "url": "https://120minutes.org/video/061790/the+church+tantalized",
      "name": "The Church | Tantalized",
      "youtubeUrl": "https://www.youtube.com/watch?v=2MEpvUfPw5Y",
      "youtubeId": "2MEpvUfPw5Y",
      "visitas": "1830",
      "fecha": "17/06/1990"
    },
    {
      "url": "https://120minutes.org/video/100790/john+wesley+harding+scared+of+guns",
      "name": "John Wesley Harding | Scared Of Guns",
      "youtubeUrl": "https://www.youtube.com/watch?v=MeBLh-24_jw",
      "youtubeId": "MeBLh-24_jw",
      "visitas": "1656",
      "fecha": "07/10/1990"
    },
    {
      "url": "https://120minutes.org/video/040890/young+fresh+fellows+picture+book",
      "name": "Young Fresh Fellows | Picture Book",
      "youtubeUrl": "https://www.youtube.com/watch?v=f8UU4gnmCP4",
      "youtubeId": "f8UU4gnmCP4",
      "visitas": "1595",
      "fecha": "08/04/1990"
    },
    {
      "url": "https://120minutes.org/video/081990/steve+wynn+carolyn",
      "name": "Steve Wynn | Carolyn",
      "youtubeUrl": "https://www.youtube.com/watch?v=vI64pWOifBw",
      "youtubeId": "vI64pWOifBw",
      "visitas": "1538",
      "fecha": "19/08/1990"
    },
    {
      "url": "https://120minutes.org/video/112590/the+water+walk+never+leaving+eden",
      "name": "The Water Walk | Never Leaving Eden",
      "youtubeUrl": "https://www.youtube.com/watch?v=ftuYEzFcUUc",
      "youtubeId": "ftuYEzFcUUc",
      "visitas": "1401",
      "fecha": "25/11/1990"
    },
    {
      "url": "https://120minutes.org/video/091690/should+she+cry+wire+train",
      "name": "Should She Cry  | Wire Train",
      "youtubeUrl": "https://www.youtube.com/watch?v=aqpLikLZpzY",
      "youtubeId": "aqpLikLZpzY",
      "visitas": "1258",
      "fecha": "16/09/1990"
    },
    {
      "url": "https://120minutes.org/video/042290/pale+saints+time+theif",
      "name": "Pale Saints | Time Theif",
      "youtubeUrl": "https://www.youtube.com/watch?v=s3U2O-UCIzc",
      "youtubeId": "s3U2O-UCIzc",
      "visitas": "1138",
      "fecha": "22/04/1990"
    },
    {
      "url": "https://120minutes.org/video/042290/mc+900+ft+jesus+with+dj+zero+im+going+straight+to+heaven",
      "name": "MC 900 Ft Jesus with DJ Zero | I'm Going Straight to Heaven",
      "youtubeUrl": "https://www.youtube.com/watch?v=rbyKZua2Ug8",
      "youtubeId": "rbyKZua2Ug8",
      "visitas": "966",
      "fecha": "22/04/1990"
    },
    {
      "url": "https://120minutes.org/video/040890/the+rave+ups+respectfully+king+of+rain",
      "name": "The Rave-Ups | Respectfully King of Rain",
      "youtubeUrl": "https://www.youtube.com/watch?v=rCovFtqk3qY",
      "youtubeId": "rCovFtqk3qY",
      "visitas": "848",
      "fecha": "08/04/1990"
    },
    {
      "url": "https://120minutes.org/video/052790/straitjacket+fits+hail",
      "name": "Straitjacket Fits | Hail",
      "youtubeUrl": "https://www.youtube.com/watch?v=syCLLhle6Wg",
      "youtubeId": "syCLLhle6Wg",
      "visitas": "817",
      "fecha": "27/05/1990"
    },
    {
      "url": "https://120minutes.org/video/040890/shane+ride+ride+ride",
      "name": "Shane | Ride, Ride, Ride",
      "youtubeUrl": "https://www.youtube.com/watch?v=3PUFCZyi3_k",
      "youtubeId": "3PUFCZyi3_k",
      "visitas": "791",
      "fecha": "08/04/1990"
    },
    {
      "url": "https://120minutes.org/video/061790/wishniaks+day+to+end+all+days",
      "name": "Wishniaks | Day To End All Days",
      "youtubeUrl": "https://www.youtube.com/watch?v=iEYr0GQg-FA",
      "youtubeId": "iEYr0GQg-FA",
      "visitas": "782",
      "fecha": "17/06/1990"
    },
    {
      "url": "https://120minutes.org/video/052790/the+pursuit+of+happiness+two+girls+in+one",
      "name": "The Pursuit Of Happiness | Two Girls in One",
      "youtubeUrl": "https://www.youtube.com/watch?v=pEvltQBOkL8",
      "youtubeId": "pEvltQBOkL8",
      "visitas": "712",
      "fecha": "27/05/1990"
    },
    {
      "url": "https://120minutes.org/video/052790/toad+the+wet+sprocket+jam",
      "name": "Toad The Wet Sprocket | Jam",
      "youtubeUrl": "https://www.youtube.com/watch?v=B9Wn6nZ714k",
      "youtubeId": "B9Wn6nZ714k",
      "visitas": "668",
      "fecha": "27/05/1990"
    },
    {
      "url": "https://120minutes.org/video/052090/the+blases+time+walks+away",
      "name": "The Blases | Time Walks Away",
      "youtubeUrl": "https://www.youtube.com/watch?v=X2XjtKr8YAI",
      "youtubeId": "X2XjtKr8YAI",
      "visitas": "642",
      "fecha": "20/05/1990"
    },
    {
      "url": "https://120minutes.org/video/082690/yo+la+tengo+the+summer",
      "name": "Yo La Tengo | The Summer",
      "youtubeUrl": "https://www.youtube.com/watch?v=14OIeJk6cto",
      "youtubeId": "14OIeJk6cto",
      "visitas": "603",
      "fecha": "26/08/1990"
    },
    {
      "url": "https://120minutes.org/video/040890/severed+heads+big+car",
      "name": "Severed Heads | Big Car",
      "youtubeUrl": "https://www.youtube.com/watch?v=2oIfnEP9Yjg",
      "youtubeId": "2oIfnEP9Yjg",
      "visitas": "512",
      "fecha": "08/04/1990"
    },
    {
      "url": "https://120minutes.org/video/052790/the+jack+rubies+book+of+love",
      "name": "The Jack Rubies | Book of Love",
      "youtubeUrl": "https://www.youtube.com/watch?v=RXIWL0eifZY",
      "youtubeId": "RXIWL0eifZY",
      "visitas": "429",
      "fecha": "27/05/1990"
    },
    {
      "url": "https://120minutes.org/video/082690/the+sneetches+heloise",
      "name": "The Sneetches | Heloise",
      "youtubeUrl": "https://www.youtube.com/watch?v=FzMQpX2aqbs",
      "youtubeId": "FzMQpX2aqbs",
      "visitas": "411",
      "fecha": "26/08/1990"
    },
    {
      "url": "https://120minutes.org/video/010790/technoid+technoid",
      "name": "Technoid | Technoid",
      "youtubeUrl": "https://www.youtube.com/watch?v=9fVWGuHiHwo",
      "youtubeId": "9fVWGuHiHwo",
      "visitas": "268",
      "fecha": "07/01/1990"
    },
    {
      "url": "https://120minutes.org/video/102190/the+heart+throbs+shes+in+a+trance",
      "name": "The Heart Throbs | She's In a Trance",
      "youtubeUrl": "https://www.youtube.com/watch?v=Z_1OjCWwutE",
      "youtubeId": "Z_1OjCWwutE",
      "visitas": "232",
      "fecha": "21/10/1990"
    },
    {
      "url": "https://120minutes.org/video/120990/killing+joke+money+is+not+our+god",
      "name": "Killing Joke | Money Is Not Our God",
      "youtubeUrl": "https://www.youtube.com/watch?v=urMwwKflD6I",
      "youtubeId": "urMwwKflD6I",
      "visitas": "227",
      "fecha": "09/12/1990"
    },
    {
      "url": "https://120minutes.org/video/071590/the+heart+throbs+dreamtime",
      "name": "The Heart Throbs | Dreamtime",
      "youtubeUrl": "https://www.youtube.com/watch?v=lPahCMyeBaE",
      "youtubeId": "lPahCMyeBaE",
      "visitas": "194",
      "fecha": "15/07/1990"
    },
    {
      "url": "https://120minutes.org/video/081990/field+trip+slumberjack",
      "name": "Field Trip | Slumberjack",
      "youtubeUrl": "https://www.youtube.com/watch?v=B9JTZ8BTFxw",
      "youtubeId": "B9JTZ8BTFxw",
      "visitas": "78",
      "fecha": "19/08/1990"
    },
    {
      "url": "https://120minutes.org/video/102890/mojo+nixon+destroy+all+lawyers",
      "name": "Mojo Nixon | Destroy All Lawyers",
      "youtubeUrl": "https://www.youtube.com/watch?v=TLMXeLS1MNE",
      "youtubeId": "TLMXeLS1MNE",
      "visitas": "38",
      "fecha": "28/10/1990"
    }
  ]
}